2023/lib/UART2WB/rtl/Uart2wb.sv
module Uart2wb 
(
    input clk,
    input rst,
    /* verilator lint_off UNUSED */
    input [7:0] UART_in_data,
    input UART_rx_done,
    output [33:0] WB_ctr_w,
    output WB_o_cyc
);

reg[4:0] asciiToBits;
reg UART_rx_done_1p;

always @(posedge clk) begin
    if (rst == 1) begin
    end else begin

        if(UART_rx_done)begin
            case (UART_in_data[6:0])
                7'h30: asciiToBits <= 5'h00;
                7'h31: asciiToBits <= 5'h01;
                7'h32: asciiToBits <= 5'h02;
                7'h33: asciiToBits <= 5'h03;
                7'h34: asciiToBits <= 5'h04;
                7'h35: asciiToBits <= 5'h05;
                7'h36: asciiToBits <= 5'h06;
                7'h37: asciiToBits <= 5'h07;
                7'h38: asciiToBits <= 5'h08;
                7'h39: asciiToBits <= 5'h09;
                7'h61: asciiToBits <= 5'h0a;
                7'h62: asciiToBits <= 5'h0b;
                7'h63: asciiToBits <= 5'h0c;
                7'h64: asciiToBits <= 5'h0d;
                7'h65: asciiToBits <= 5'h0e;
                7'h66: asciiToBits <= 5'h0f;
                7'h52: asciiToBits <= 5'h10; // R
                7'h57: asciiToBits <= 5'h11; // W
                7'h41: asciiToBits <= 5'h12; // A
                7'h53: asciiToBits <= 5'h13; // S - bude se jednat o reset
                7'h54: asciiToBits <= 5'h16; // T

            default:    //other character, are ignored
                        //nebo jako end of word character
                asciiToBits <= 5'h1f;
            endcase
        end

        UART_rx_done_1p <= UART_rx_done;
    end
end

reg [33:0] WB_ctr_w_r;
reg [33:0] WB_ctr_w_o;
reg WB_o_cyc_r;



always @(posedge clk) begin
    if(rst == 1) begin
    end else begin
        WB_o_cyc_r <= 0;
        if(UART_rx_done_1p) begin   //priznak, dalsiho pismene z uartu, zpozdene o jednu peridou
            if(asciiToBits[4] == 1) begin   //prikazy R,W,A,S,T
                WB_o_cyc_r <= 1;    //pokud jsou to prikazy, odeslat soucasne hodnoty ulozene v WB_ctr_w_r dále
                WB_ctr_w_o <= WB_ctr_w_r;
                WB_ctr_w_r[33:32] <= asciiToBits[1:0]; //ale tohle neplati pro T, todo!!!! 
                WB_ctr_w_r[31:0] <= 0;
            end else begin
                WB_ctr_w_r[31:0] <= {WB_ctr_w_r[27:0],asciiToBits[3:0]};  
            end
            
        end
    end
end

assign WB_o_cyc = WB_o_cyc_r;
assign WB_ctr_w = WB_ctr_w_o;


endmodule

2023/lib/UART2WB/sim/top_Uart2wb.sv
typedef enum logic [1:0] {
     add     = 2'h1,
     sub     = 2'h2,
     nop     = 2'h0
} operation_t /*verilator public*/;

module top_Uart2wb 
(
	input clk,
     input rst,
	input [7:0] UART_in_data,
	input UART_Rx_done,
     output [33:0] WB_ctr_w,
     output WB_o_cyc

);

Uart2wb U2W(.clk(clk), .rst(rst), .UART_in_data(UART_in_data), .UART_rx_done(UART_Rx_done), .WB_ctr_w(WB_ctr_w), .WB_o_cyc(WB_o_cyc));

endmodule

2023/lib/UART2WB/sim/waveform.vcd
$version Generated by VerilatedVcd $end
$date Sun Oct 16 17:20:17 2022
 $end
$timescale   1ps $end

 $scope module TOP $end
  $var wire  1 - UART_Rx_done $end
  $var wire  8 , UART_in_data [7:0] $end
  $var wire 34 . WB_ctr_w [33:0] $end
  $var wire  1 0 WB_o_cyc $end
  $var wire  1 * clk $end
  $var wire  1 + rst $end
  $scope module top_Uart2wb $end
   $var wire  1 - UART_Rx_done $end
   $var wire  8 , UART_in_data [7:0] $end
   $var wire 34 . WB_ctr_w [33:0] $end
   $var wire  1 0 WB_o_cyc $end
   $var wire  1 * clk $end
   $var wire  1 + rst $end
   $scope module U2W $end
    $var wire  8 , UART_in_data [7:0] $end
    $var wire  1 - UART_rx_done $end
    $var wire  1 $ UART_rx_done_1p $end
    $var wire 34 . WB_ctr_w [33:0] $end
    $var wire 34 ' WB_ctr_w_o [33:0] $end
    $var wire 34 % WB_ctr_w_r [33:0] $end
    $var wire  1 0 WB_o_cyc $end
    $var wire  1 ) WB_o_cyc_r $end
    $var wire  5 # asciiToBits [4:0] $end
    $var wire  1 * clk $end
    $var wire  1 + rst $end
   $upscope $end
  $upscope $end
 $upscope $end
$enddefinitions $end


#0
b00000 #
0$
b0000000000000000000000000000000000 %
b0000000000000000000000000000000000 '
0)
1*
0+
b00000000 ,
0-
b0000000000000000000000000000000000 .
00
#1
0*
#2
1*
#3
0*
#4
1*
#5
0*
#6
1*
#7
0*
#8
1*
#9
0*
#10
1*
#11
0*
#12
1*
#13
0*
#14
1*
#15
0*
#16
1*
#17
0*
#18
1*
#19
0*
#20
1*
#21
0*
#22
1*
b01000001 ,
1-
#23
0*
#24
b10010 #
1$
1*
0-
#25
0*
#26
0$
b1000000000000000000000000000000000 %
1)
1*
10
#27
0*
#28
0)
1*
00
#29
0*
#30
1*
#31
0*
#32
1*
#33
0*
#34
1*
b00110010 ,
1-
#35
0*
#36
b00010 #
1$
1*
0-
#37
0*
#38
0$
b1000000000000000000000000000000010 %
1*
#39
0*
#40
1*
#41
0*
#42
1*
#43
0*
#44
1*
#45
0*
#46
1*
b01010010 ,
1-
#47
0*
#48
b10000 #
1$
1*
0-
#49
0*
#50
0$
b0000000000000000000000000000000000 %
b1000000000000000000000000000000010 '
1)
1*
b1000000000000000000000000000000010 .
10
#51
0*
#52
0)
1*
00
#53
0*
#54
1*
#55
0*
#56
1*
#57
0*
#58
1*
b01000001 ,
1-
#59
0*
#60
b10010 #
1$
1*
0-
#61
0*
#62
0$
b1000000000000000000000000000000000 %
b0000000000000000000000000000000000 '
1)
1*
b0000000000000000000000000000000000 .
10
#63
0*
#64
0)
1*
00
#65
0*
#66
1*
#67
0*
#68
1*
#69
0*
#70
1*
b00110100 ,
1-
#71
0*
#72
b00100 #
1$
1*
0-
#73
0*
#74
0$
b1000000000000000000000000000000100 %
1*
#75
0*
#76
1*
#77
0*
#78
1*
#79
0*
#80
1*
#81
0*
#82
1*
b01010111 ,
1-
#83
0*
#84
b10001 #
1$
1*
0-
#85
0*
#86
0$
b0100000000000000000000000000000000 %
b1000000000000000000000000000000100 '
1)
1*
b1000000000000000000000000000000100 .
10
#87
0*
#88
0)
1*
00
#89
0*
#90
1*
#91
0*
#92
1*
#93
0*
#94
1*
b00110010 ,
1-
#95
0*
#96
b00010 #
1$
1*
0-
#97
0*
#98
0$
b0100000000000000000000000000000010 %
1*
#99
0*
#100
1*
#101
0*
#102
1*
#103
0*
#104
1*
#105
0*
#106
1*
b01000001 ,
1-
#107
0*
#108
b10010 #
1$
1*
0-
#109
0*
#110
0$
b1000000000000000000000000000000000 %
b0100000000000000000000000000000010 '
1)
1*
b0100000000000000000000000000000010 .
10
#111
0*
#112
0)
1*
00
#113
0*
#114
1*
#115
0*
#116
1*
#117
0*
#118
1*
b00110001 ,
1-
#119
0*
#120
b00001 #
1$
1*
0-
#121
0*
#122
0$
b1000000000000000000000000000000001 %
1*
#123
0*
#124
1*
#125
0*
#126
1*
#127
0*
#128
1*
#129
0*
#130
1*
1-
#131
0*
#132
1$
1*
0-
#133
0*
#134
0$
b1000000000000000000000000000010001 %
1*
#135
0*
#136
1*
#137
0*
#138
1*
#139
0*
#140
1*
#141
0*
#142
1*
b00110010 ,
1-
#143
0*
#144
b00010 #
1$
1*
0-
#145
0*
#146
0$
b1000000000000000000000000100010010 %
1*
#147
0*
#148
1*
#149
0*
#150
1*
#151
0*
#152
1*
#153
0*
#154
1*
b01010010 ,
1-
#155
0*
#156
b10000 #
1$
1*
0-
#157
0*
#158
0$
b0000000000000000000000000000000000 %
b1000000000000000000000000100010010 '
1)
1*
b1000000000000000000000000100010010 .
10
#159
0*
#160
0)
1*
00
#161
0*
#162
1*
#163
0*
#164
1*
#165
0*
#166
1*
b01000001 ,
1-
#167
0*
#168
b10010 #
1$
1*
0-
#169
0*
#170
0$
b1000000000000000000000000000000000 %
b0000000000000000000000000000000000 '
1)
1*
b0000000000000000000000000000000000 .
10
#171
0*
#172
0)
1*
00
#173
0*
#174
1*
#175
0*
#176
1*
#177
0*
#178
1*
b00110010 ,
1-
#179
0*
#180
b00010 #
1$
1*
0-
#181
0*
#182
0$
b1000000000000000000000000000000010 %
1*
#183
0*
#184
1*
#185
0*
#186
1*
#187
0*
#188
1*
#189
0*
#190
1*
b01010010 ,
1-
#191
0*
#192
b10000 #
1$
1*
0-
#193
0*
#194
0$
b0000000000000000000000000000000000 %
b1000000000000000000000000000000010 '
1)
1*
b1000000000000000000000000000000010 .
10
#195
0*
#196
0)
1*
00
#197
0*
#198
1*
#199
0*
#200
1*
#201
0*
#202
1*
b01000001 ,
1-
#203
0*
#204
b10010 #
1$
1*
0-
#205
0*
#206
0$
b1000000000000000000000000000000000 %
b0000000000000000000000000000000000 '
1)
1*
b0000000000000000000000000000000000 .
10
#207
0*
#208
0)
1*
00
#209
0*
#210
1*
#211
0*
#212
1*
#213
0*
#214
1*
b00110100 ,
1-
#215
0*
#216
b00100 #
1$
1*
0-
#217
0*
#218
0$
b1000000000000000000000000000000100 %
1*
#219
0*
#220
1*
#221
0*
#222
1*
#223
0*
#224
1*
#225
0*
#226
1*
b01010111 ,
1-
#227
0*
#228
b10001 #
1$
1*
0-
#229
0*
#230
0$
b0100000000000000000000000000000000 %
b1000000000000000000000000000000100 '
1)
1*
b1000000000000000000000000000000100 .
10
#231
0*
#232
0)
1*
00
#233
0*
#234
1*
#235
0*
#236
1*
#237
0*
#238
1*
b00110010 ,
1-
#239
0*
#240
b00010 #
1$
1*
0-
#241
0*
#242
0$
b0100000000000000000000000000000010 %
1*
#243
0*
#244
1*
#245
0*
#246
1*
#247
0*
#248
1*
#249
0*
#250
1*
b01000001 ,
1-
#251
0*
#252
b10010 #
1$
1*
0-
#253
0*
#254
0$
b1000000000000000000000000000000000 %
b0100000000000000000000000000000010 '
1)
1*
b0100000000000000000000000000000010 .
10
#255
0*
#256
0)
1*
00
#257
0*
#258
1*
#259
0*
#260
1*
#261
0*
#262
1*
b00110001 ,
1-
#263
0*
#264
b00001 #
1$
1*
0-
#265
0*
#266
0$
b1000000000000000000000000000000001 %
1*
#267
0*
#268
1*
#269
0*
#270
1*
#271
0*
#272
1*
#273
0*
#274
1*
1-
#275
0*
#276
1$
1*
0-
#277
0*
#278
0$
b1000000000000000000000000000010001 %
1*
#279
0*
#280
1*
#281
0*
#282
1*
#283
0*
#284
1*
#285
0*
#286
1*
b00110010 ,
1-
#287
0*
#288
b00010 #
1$
1*
0-
#289
0*
#290
0$
b1000000000000000000000000100010010 %
1*
#291
0*
#292
1*
#293
0*
#294
1*
#295
0*
#296
1*
#297
0*
#298
1*
b01010010 ,
1-
#299
0*
#300
b10000 #
1$
1*
0-
#301
0*
#302
0$
b0000000000000000000000000000000000 %
b1000000000000000000000000100010010 '
1)
1*
b1000000000000000000000000100010010 .
10
#303
0*
#304
0)
1*
00
#305
0*
#306
1*
#307
0*
#308
1*
#309
0*
#310
1*
b01000001 ,
1-
#311
0*
#312
b10010 #
1$
1*
0-
#313
0*
#314
0$
b1000000000000000000000000000000000 %
b0000000000000000000000000000000000 '
1)
1*
b0000000000000000000000000000000000 .
10
#315
0*
#316
0)
1*
00
#317
0*
#318
1*
#319
0*
#320
1*
#321
0*
#322
1*
b00110010 ,
1-
#323
0*
#324
b00010 #
1$
1*
0-
#325
0*
#326
0$
b1000000000000000000000000000000010 %
1*
#327
0*
#328
1*
#329
0*
#330
1*
#331
0*
#332
1*
#333
0*
#334
1*
b01010010 ,
1-
#335
0*
#336
b10000 #
1$
1*
0-
#337
0*
#338
0$
b0000000000000000000000000000000000 %
b1000000000000000000000000000000010 '
1)
1*
b1000000000000000000000000000000010 .
10
#339
0*
#340
0)
1*
00
#341
0*
#342
1*
#343
0*
#344
1*
#345
0*
#346
1*
b01000001 ,
1-
#347
0*
#348
b10010 #
1$
1*
0-
#349
0*
#350
0$
b1000000000000000000000000000000000 %
b0000000000000000000000000000000000 '
1)
1*
b0000000000000000000000000000000000 .
10
#351
0*
#352
0)
1*
00
#353
0*
#354
1*
#355
0*
#356
1*
#357
0*
#358
1*
b00110100 ,
1-
#359
0*
#360
b00100 #
1$
1*
0-
#361
0*
#362
0$
b1000000000000000000000000000000100 %
1*
#363
0*
#364
1*
#365
0*
#366
1*
#367
0*
#368
1*
#369
0*
#370
1*
b01010111 ,
1-
#371
0*
#372
b10001 #
1$
1*
0-
#373
0*
#374
0$
b0100000000000000000000000000000000 %
b1000000000000000000000000000000100 '
1)
1*
b1000000000000000000000000000000100 .
10
#375
0*
#376
0)
1*
00
#377
0*
#378
1*
#379
0*
#380
1*
#381
0*
#382
1*
b00110010 ,
1-
#383
0*
#384
b00010 #
1$
1*
0-
#385
0*
#386
0$
b0100000000000000000000000000000010 %
1*
#387
0*
#388
1*
#389
0*
#390
1*
#391
0*
#392
1*
#393
0*
#394
1*
b01000001 ,
1-
#395
0*
#396
b10010 #
1$
1*
0-
#397
0*
#398
0$
b1000000000000000000000000000000000 %
b0100000000000000000000000000000010 '
1)
1*
b0100000000000000000000000000000010 .
10
#399
0*
#400
0)
1*
00
#401
0*
#402
1*
#403
0*
#404
1*
#405
0*
#406
1*
b00110001 ,
1-
#407
0*
#408
b00001 #
1$
1*
0-
#409
0*
#410
0$
b1000000000000000000000000000000001 %
1*
#411
0*
#412
1*
#413
0*
#414
1*
#415
0*
#416
1*
#417
0*
#418
1*
1-
#419
0*
#420
1$
1*
0-
#421
0*
#422
0$
b1000000000000000000000000000010001 %
1*
#423
0*
#424
1*
#425
0*
#426
1*
#427
0*
#428
1*
#429
0*
#430
1*
b00110010 ,
1-
#431
0*
#432
b00010 #
1$
1*
0-
#433
0*
#434
0$
b1000000000000000000000000100010010 %
1*
#435
0*
#436
1*
#437
0*
#438
1*
#439
0*
#440
1*
#441
0*
#442
1*
b01010010 ,
1-
#443
0*
#444
b10000 #
1$
1*
0-
#445
0*
#446
0$
b0000000000000000000000000000000000 %
b1000000000000000000000000100010010 '
1)
1*
b1000000000000000000000000100010010 .
10
#447
0*
#448
0)
1*
00
#449
0*
#450
1*
#451
0*
#452
1*
#453
0*
#454
1*
b01000001 ,
1-
#455
0*
#456
b10010 #
1$
1*
0-
#457
0*
#458
0$
b1000000000000000000000000000000000 %
b0000000000000000000000000000000000 '
1)
1*
b0000000000000000000000000000000000 .
10
#459
0*
#460
0)
1*
00
#461
0*
#462
1*
#463
0*
#464
1*
#465
0*
#466
1*
b00110010 ,
1-
#467
0*
#468
b00010 #
1$
1*
0-
#469
0*
#470
0$
b1000000000000000000000000000000010 %
1*
#471
0*
#472
1*
#473
0*
#474
1*
#475
0*
#476
1*
#477
0*
#478
1*
b01010010 ,
1-
#479
0*
#480
b10000 #
1$
1*
0-
#481
0*
#482
0$
b0000000000000000000000000000000000 %
b1000000000000000000000000000000010 '
1)
1*
b1000000000000000000000000000000010 .
10
#483
0*
#484
0)
1*
00
#485
0*
#486
1*
#487
0*
#488
1*
#489
0*
#490
1*
b01000001 ,
1-
#491
0*
#492
b10010 #
1$
1*
0-
#493
0*
#494
0$
b1000000000000000000000000000000000 %
b0000000000000000000000000000000000 '
1)
1*
b0000000000000000000000000000000000 .
10
#495
0*
#496
0)
1*
00
#497
0*
#498
1*
#499
0*
#500
1*
#501
0*
#502
1*
b00110100 ,
1-
#503
0*
#504
b00100 #
1$
1*
0-
#505
0*
#506
0$
b1000000000000000000000000000000100 %
1*
#507
0*
#508
1*
#509
0*
#510
1*
#511
0*
#512
1*
#513
0*
#514
1*
b01010111 ,
1-
#515
0*
#516
b10001 #
1$
1*
0-
#517
0*
#518
0$
b0100000000000000000000000000000000 %
b1000000000000000000000000000000100 '
1)
1*
b1000000000000000000000000000000100 .
10
#519
0*
#520
0)
1*
00
#521
0*
#522
1*
#523
0*
#524
1*
#525
0*
#526
1*
b00110010 ,
1-
#527
0*
#528
b00010 #
1$
1*
0-
#529
0*
#530
0$
b0100000000000000000000000000000010 %
1*
#531
0*
#532
1*
#533
0*
#534
1*
#535
0*
#536
1*
#537
0*
#538
1*
b01000001 ,
1-
#539
0*
#540
b10010 #
1$
1*
0-
#541
0*
#542
0$
b1000000000000000000000000000000000 %
b0100000000000000000000000000000010 '
1)
1*
b0100000000000000000000000000000010 .
10
#543
0*
#544
0)
1*
00
#545
0*
#546
1*
#547
0*
#548
1*
#549
0*
#550
1*
b00110001 ,
1-
#551
0*
#552
b00001 #
1$
1*
0-
#553
0*
#554
0$
b1000000000000000000000000000000001 %
1*
#555
0*
#556
1*
#557
0*
#558
1*
#559
0*
#560
1*
#561
0*
#562
1*
1-
#563
0*
#564
1$
1*
0-
#565
0*
#566
0$
b1000000000000000000000000000010001 %
1*
#567
0*
#568
1*
#569
0*
#570
1*
#571
0*
#572
1*
#573
0*
#574
1*
b00110010 ,
1-
#575
0*
#576
b00010 #
1$
1*
0-
#577
0*
#578
0$
b1000000000000000000000000100010010 %
1*
#579
0*
#580
1*
#581
0*
#582
1*
#583
0*
#584
1*
#585
0*
#586
1*
b01010010 ,
1-
#587
0*
#588
b10000 #
1$
1*
0-
#589
0*
#590
0$
b0000000000000000000000000000000000 %
b1000000000000000000000000100010010 '
1)
1*
b1000000000000000000000000100010010 .
10
#591
0*
#592
0)
1*
00
#593
0*
#594
1*
#595
0*
#596
1*
#597
0*
#598
1*
b01000001 ,
1-
#599
0*
#600
b10010 #
1$
1*
0-
#601
0*
#602
0$
b1000000000000000000000000000000000 %
b0000000000000000000000000000000000 '
1)
1*
b0000000000000000000000000000000000 .
10
#603
0*
#604
0)
1*
00
#605
0*
#606
1*
#607
0*
#608
1*
#609
0*
#610
1*
b00110010 ,
1-
#611
0*
#612
b00010 #
1$
1*
0-
#613
0*
#614
0$
b1000000000000000000000000000000010 %
1*
#615
0*
#616
1*
#617
0*
#618
1*
#619
0*
#620
1*
#621
0*
#622
1*
b01010010 ,
1-
#623
0*
#624
b10000 #
1$
1*
0-
#625
0*
#626
0$
b0000000000000000000000000000000000 %
b1000000000000000000000000000000010 '
1)
1*
b1000000000000000000000000000000010 .
10
#627
0*
#628
0)
1*
00
#629
0*
#630
1*
#631
0*
#632
1*
#633
0*
#634
1*
b01000001 ,
1-
#635
0*
#636
b10010 #
1$
1*
0-
#637
0*
#638
0$
b1000000000000000000000000000000000 %
b0000000000000000000000000000000000 '
1)
1*
b0000000000000000000000000000000000 .
10
#639
0*
#640
0)
1*
00
#641
0*
#642
1*
#643
0*
#644
1*
#645
0*
#646
1*
b00110100 ,
1-
#647
0*
#648
b00100 #
1$
1*
0-
#649
0*
#650
0$
b1000000000000000000000000000000100 %
1*
#651
0*
#652
1*
#653
0*
#654
1*
#655
0*
#656
1*
#657
0*
#658
1*
b01010111 ,
1-
#659
0*
#660
b10001 #
1$
1*
0-
#661
0*
#662
0$
b0100000000000000000000000000000000 %
b1000000000000000000000000000000100 '
1)
1*
b1000000000000000000000000000000100 .
10
#663
0*
#664
0)
1*
00
#665
0*
#666
1*
#667
0*
#668
1*
#669
0*
#670
1*
b00110010 ,
1-
#671
0*
#672
b00010 #
1$
1*
0-
#673
0*
#674
0$
b0100000000000000000000000000000010 %
1*
#675
0*
#676
1*
#677
0*
#678
1*
#679
0*
#680
1*
#681
0*
#682
1*
b01000001 ,
1-
#683
0*
#684
b10010 #
1$
1*
0-
#685
0*
#686
0$
b1000000000000000000000000000000000 %
b0100000000000000000000000000000010 '
1)
1*
b0100000000000000000000000000000010 .
10
#687
0*
#688
0)
1*
00
#689
0*
#690
1*
#691
0*
#692
1*
#693
0*
#694
1*
b00110001 ,
1-
#695
0*
#696
b00001 #
1$
1*
0-
#697
0*
#698
0$
b1000000000000000000000000000000001 %
1*
#699
0*
#700
1*
#701
0*
#702
1*
#703
0*
#704
1*
#705
0*
#706
1*
1-
#707
0*
#708
1$
1*
0-
#709
0*
#710
0$
b1000000000000000000000000000010001 %
1*
#711
0*
#712
1*
#713
0*
#714
1*
#715
0*
#716
1*
#717
0*
#718
1*
b00110010 ,
1-
#719
0*
#720
b00010 #
1$
1*
0-
#721
0*
#722
0$
b1000000000000000000000000100010010 %
1*
#723
0*
#724
1*
#725
0*
#726
1*
#727
0*
#728
1*
#729
0*
#730
1*
b01010010 ,
1-
#731
0*
#732
b10000 #
1$
1*
0-
#733
0*
#734
0$
b0000000000000000000000000000000000 %
b1000000000000000000000000100010010 '
1)
1*
b1000000000000000000000000100010010 .
10
#735
0*
#736
0)
1*
00
#737
0*
#738
1*
#739
0*
#740
1*
#741
0*
#742
1*
b01000001 ,
1-
#743
0*
#744
b10010 #
1$
1*
0-
#745
0*
#746
0$
b1000000000000000000000000000000000 %
b0000000000000000000000000000000000 '
1)
1*
b0000000000000000000000000000000000 .
10
#747
0*
#748
0)
1*
00
#749
0*
#750
1*
#751
0*
#752
1*
#753
0*
#754
1*
b00110010 ,
1-
#755
0*
#756
b00010 #
1$
1*
0-
#757
0*
#758
0$
b1000000000000000000000000000000010 %
1*
#759
0*
#760
1*
#761
0*
#762
1*
#763
0*
#764
1*
#765
0*
#766
1*
b01010010 ,
1-
#767
0*
#768
b10000 #
1$
1*
0-
#769
0*
#770
0$
b0000000000000000000000000000000000 %
b1000000000000000000000000000000010 '
1)
1*
b1000000000000000000000000000000010 .
10
#771
0*
#772
0)
1*
00
#773
0*
#774
1*
#775
0*
#776
1*
#777
0*
#778
1*
b01000001 ,
1-
#779
0*
#780
b10010 #
1$
1*
0-
#781
0*
#782
0$
b1000000000000000000000000000000000 %
b0000000000000000000000000000000000 '
1)
1*
b0000000000000000000000000000000000 .
10
#783
0*
#784
0)
1*
00
#785
0*
#786
1*
#787
0*
#788
1*
#789
0*
#790
1*
b00110100 ,
1-
#791
0*
#792
b00100 #
1$
1*
0-
#793
0*
#794
0$
b1000000000000000000000000000000100 %
1*
#795
0*
#796
1*
#797
0*
#798
1*
#799
0*
#800
1*
#801
0*
#802
1*
b01010111 ,
1-
#803
0*
#804
b10001 #
1$
1*
0-
#805
0*
#806
0$
b0100000000000000000000000000000000 %
b1000000000000000000000000000000100 '
1)
1*
b1000000000000000000000000000000100 .
10
#807
0*
#808
0)
1*
00
#809
0*
#810
1*
#811
0*
#812
1*
#813
0*
#814
1*
b00110010 ,
1-
#815
0*
#816
b00010 #
1$
1*
0-
#817
0*
#818
0$
b0100000000000000000000000000000010 %
1*
#819
0*
#820
1*
#821
0*
#822
1*
#823
0*
#824
1*
#825
0*
#826
1*
b01000001 ,
1-
#827
0*
#828
b10010 #
1$
1*
0-
#829
0*
#830
0$
b1000000000000000000000000000000000 %
b0100000000000000000000000000000010 '
1)
1*
b0100000000000000000000000000000010 .
10
#831
0*
#832
0)
1*
00
#833
0*
#834
1*
#835
0*
#836
1*
#837
0*
#838
1*
b00110001 ,
1-
#839
0*
#840
b00001 #
1$
1*
0-
#841
0*
#842
0$
b1000000000000000000000000000000001 %
1*
#843
0*
#844
1*
#845
0*
#846
1*
#847
0*
#848
1*
#849
0*
#850
1*
1-
#851
0*
#852
1$
1*
0-
#853
0*
#854
0$
b1000000000000000000000000000010001 %
1*
#855
0*
#856
1*
#857
0*
#858
1*
#859
0*
#860
1*
#861
0*
#862
1*
b00110010 ,
1-
#863
0*
#864
b00010 #
1$
1*
0-
#865
0*
#866
0$
b1000000000000000000000000100010010 %
1*
#867
0*
#868
1*
#869
0*
#870
1*
#871
0*
#872
1*
#873
0*
#874
1*
b01010010 ,
1-
#875
0*
#876
b10000 #
1$
1*
0-
#877
0*
#878
0$
b0000000000000000000000000000000000 %
b1000000000000000000000000100010010 '
1)
1*
b1000000000000000000000000100010010 .
10
#879
0*
#880
0)
1*
00
#881
0*
#882
1*
#883
0*
#884
1*
#885
0*
#886
1*
b01000001 ,
1-
#887
0*
#888
b10010 #
1$
1*
0-
#889
0*
#890
0$
b1000000000000000000000000000000000 %
b0000000000000000000000000000000000 '
1)
1*
b0000000000000000000000000000000000 .
10
#891
0*
#892
0)
1*
00
#893
0*
#894
1*
#895
0*
#896
1*
#897
0*
#898
1*
b00110010 ,
1-
#899
0*
#900
b00010 #
1$
1*
0-
#901
0*
#902
0$
b1000000000000000000000000000000010 %
1*
#903
0*
#904
1*
#905
0*
#906
1*
#907
0*
#908
1*
#909
0*
#910
1*
b01010010 ,
1-
#911
0*
#912
b10000 #
1$
1*
0-
#913
0*
#914
0$
b0000000000000000000000000000000000 %
b1000000000000000000000000000000010 '
1)
1*
b1000000000000000000000000000000010 .
10
#915
0*
#916
0)
1*
00
#917
0*
#918
1*
#919
0*
#920
1*
#921
0*
#922
1*
b01000001 ,
1-
#923
0*
#924
b10010 #
1$
1*
0-
#925
0*
#926
0$
b1000000000000000000000000000000000 %
b0000000000000000000000000000000000 '
1)
1*
b0000000000000000000000000000000000 .
10
#927
0*
#928
0)
1*
00
#929
0*
#930
1*
#931
0*
#932
1*
#933
0*
#934
1*
b00110100 ,
1-
#935
0*
#936
b00100 #
1$
1*
0-
#937
0*
#938
0$
b1000000000000000000000000000000100 %
1*
#939
0*
#940
1*
#941
0*
#942
1*
#943
0*
#944
1*
#945
0*
#946
1*
b01010111 ,
1-
#947
0*
#948
b10001 #
1$
1*
0-
#949
0*
#950
0$
b0100000000000000000000000000000000 %
b1000000000000000000000000000000100 '
1)
1*
b1000000000000000000000000000000100 .
10
#951
0*
#952
0)
1*
00
#953
0*
#954
1*
#955
0*
#956
1*
#957
0*
#958
1*
b00110010 ,
1-
#959
0*
#960
b00010 #
1$
1*
0-
#961
0*
#962
0$
b0100000000000000000000000000000010 %
1*
#963
0*
#964
1*
#965
0*
#966
1*
#967
0*
#968
1*
#969
0*
#970
1*
b01000001 ,
1-
#971
0*
#972
b10010 #
1$
1*
0-
#973
0*
#974
0$
b1000000000000000000000000000000000 %
b0100000000000000000000000000000010 '
1)
1*
b0100000000000000000000000000000010 .
10
#975
0*
#976
0)
1*
00
#977
0*
#978
1*
#979
0*
#980
1*
#981
0*
#982
1*
b00110001 ,
1-
#983
0*
#984
b00001 #
1$
1*
0-
#985
0*
#986
0$
b1000000000000000000000000000000001 %
1*
#987
0*
#988
1*
#989
0*
#990
1*
#991
0*
#992
1*
#993
0*
#994
1*
1-
#995
0*
#996
1$
1*
0-
#997
0*
#998
0$
b1000000000000000000000000000010001 %
1*
#999
0*
#1000
1*
#1001
0*
#1002
1*
#1003
0*
#1004
1*
#1005
0*
#1006
1*
b00110010 ,
1-
#1007
0*
#1008
b00010 #
1$
1*
0-
#1009
0*
#1010
0$
b1000000000000000000000000100010010 %
1*
#1011
0*
#1012
1*
#1013
0*
#1014
1*
#1015
0*
#1016
1*
#1017
0*
#1018
1*
b01010010 ,
1-
#1019
0*
#1020
b10000 #
1$
1*
0-
#1021
0*
#1022
0$
b0000000000000000000000000000000000 %
b1000000000000000000000000100010010 '
1)
1*
b1000000000000000000000000100010010 .
10
#1023
0*
#1024
0)
1*
00
#1025
0*
#1026
1*
#1027
0*
#1028
1*
#1029
0*
#1030
1*
b01000001 ,
1-
#1031
0*
#1032
b10010 #
1$
1*
0-
#1033
0*
#1034
0$
b1000000000000000000000000000000000 %
b0000000000000000000000000000000000 '
1)
1*
b0000000000000000000000000000000000 .
10
#1035
0*
#1036
0)
1*
00
#1037
0*
#1038
1*
#1039
0*
#1040
1*
#1041
0*
#1042
1*
b00110010 ,
1-
#1043
0*
#1044
b00010 #
1$
1*
0-
#1045
0*
#1046
0$
b1000000000000000000000000000000010 %
1*
#1047
0*
#1048
1*
#1049
0*
#1050
1*
#1051
0*
#1052
1*
#1053
0*
#1054
1*
b01010010 ,
1-
#1055
0*
#1056
b10000 #
1$
1*
0-
#1057
0*
#1058
0$
b0000000000000000000000000000000000 %
b1000000000000000000000000000000010 '
1)
1*
b1000000000000000000000000000000010 .
10
#1059
0*
#1060
0)
1*
00
#1061
0*
#1062
1*
#1063
0*
#1064
1*
#1065
0*
#1066
1*
b01000001 ,
1-
#1067
0*
#1068
b10010 #
1$
1*
0-
#1069
0*
#1070
0$
b1000000000000000000000000000000000 %
b0000000000000000000000000000000000 '
1)
1*
b0000000000000000000000000000000000 .
10
#1071
0*
#1072
0)
1*
00
#1073
0*
#1074
1*
#1075
0*
#1076
1*
#1077
0*
#1078
1*
b00110100 ,
1-
#1079
0*
#1080
b00100 #
1$
1*
0-
#1081
0*
#1082
0$
b1000000000000000000000000000000100 %
1*
#1083
0*
#1084
1*
#1085
0*
#1086
1*
#1087
0*
#1088
1*
#1089
0*
#1090
1*
b01010111 ,
1-
#1091
0*
#1092
b10001 #
1$
1*
0-
#1093
0*
#1094
0$
b0100000000000000000000000000000000 %
b1000000000000000000000000000000100 '
1)
1*
b1000000000000000000000000000000100 .
10
#1095
0*
#1096
0)
1*
00
#1097
0*
#1098
1*
#1099
0*
#1100
1*
#1101
0*
#1102
1*
b00110010 ,
1-
#1103
0*
#1104
b00010 #
1$
1*
0-
#1105
0*
#1106
0$
b0100000000000000000000000000000010 %
1*
#1107
0*
#1108
1*
#1109
0*
#1110
1*
#1111
0*
#1112
1*
#1113
0*
#1114
1*
b01000001 ,
1-
#1115
0*
#1116
b10010 #
1$
1*
0-
#1117
0*
#1118
0$
b1000000000000000000000000000000000 %
b0100000000000000000000000000000010 '
1)
1*
b0100000000000000000000000000000010 .
10
#1119
0*
#1120
0)
1*
00
#1121
0*
#1122
1*
#1123
0*
#1124
1*
#1125
0*
#1126
1*
b00110001 ,
1-
#1127
0*
#1128
b00001 #
1$
1*
0-
#1129
0*
#1130
0$
b1000000000000000000000000000000001 %
1*
#1131
0*
#1132
1*
#1133
0*
#1134
1*
#1135
0*
#1136
1*
#1137
0*
#1138
1*
1-
#1139
0*
#1140
1$
1*
0-
#1141
0*
#1142
0$
b1000000000000000000000000000010001 %
1*
#1143
0*
#1144
1*
#1145
0*
#1146
1*
#1147
0*
