wishbone/UartTx.sv
module UartTx #(parameter KBAUD = 14'd10416)
(
    input clk,
    input [7:0] in_DataByte,  /* data, which you have want to send*/
    input in_Start,           /* start of the translation*/
    output out_DataBit,       /* data which are sent to the output*/
    output out_fComplete      /* flag of idle state/ idle = 1 */
);
    
localparam s_START = 0; /*neco jako idle stav, kdy pri pozadavku na odeslani dat, se nastaví výstup*/
localparam s_DATA  = 1;
localparam s_STOP  = 2;

reg [1:0] state = s_START;
reg [$clog2(KBAUD)-1:0]baud_cnt = 0;

reg [7:0] Data;
reg [3:0] r_data_cnt = 0;

reg r_out_dataBit;
reg r_out_fComplete;



always @(posedge clk) begin

    if(baud_cnt == 0) begin

        case (state)
            s_START:begin
                if((in_Start == 0)&&(r_out_fComplete == 1)) begin           // && r_out_fComplete - tohle zalezi na nadrazeny casti, nesmi drzet start na 1
                    Data <= in_DataByte;
                    state <= s_DATA;
                    baud_cnt <= KBAUD - 1;
                    r_data_cnt <= 0;
                    r_out_fComplete <= 0;   // translation is processing
                    r_out_dataBit <= 0;
                end else begin
                    baud_cnt <= 0;
                    r_out_fComplete <= 1; // translation is end, or in IDLE
                    r_out_dataBit <= 1;
                end
            end s_DATA:begin
                r_out_dataBit <= Data[r_data_cnt];
                
                if(r_data_cnt == 7) begin
                    state <= s_STOP;
                end
                r_data_cnt <= r_data_cnt + 1;
                baud_cnt <= KBAUD - 1;
            end s_STOP:begin
                baud_cnt <= KBAUD - 1;
                state <= s_START;
                r_out_dataBit <= 1;
                
            end default:begin end 
        endcase

    end else begin
        baud_cnt <= baud_cnt - 1;
    end

end


assign out_DataBit = r_out_dataBit;
assign out_fComplete = r_out_fComplete;

endmodule

2023/lib/WB2UART/rtl/WB2UART.sv
module WB2UART
(
    input clk,
    input rst,
    
    //prikazy z mastera
    /* verilator lint_off UNUSED */
    input [33:0] in_WB2UART_word,
    input        in_WB2UART_cyc,

    //prikazi pro UartTx transmitera (lib/UART/rtl/UartTx.sv)
    /* verilator lint_off UNDRIVEN */
    output [7:0] out_DataByte,  // pozadovane pismeno k odeslani
    output       out_Start,     // pozadavek pro odeslani dalsiho pisnema
    input        in_fComplete   // prenos pismene, hotov
);

reg[3:0] index;
reg ted;
reg in_fComplete_old;
wire in_fComplete_r;

always @(posedge clk) begin
    ted <= 0;
    if(rst) begin
        index <= 0;
        in_fComplete_old <= 0;
    end else begin
        if(in_WB2UART_cyc) begin
            index <= 8;  
            ted <= 1;     
        end
    end

    if((in_fComplete_r || ted) && (index > 0)) begin

        index <= index - 1;
    end

    in_fComplete_old <= in_fComplete;
end

assign in_fComplete_r = in_fComplete & (~in_fComplete_old);


endmodule

2023/wbMaster/rtl/WbMaster.sv
module WbMaster
(
    input clk, 
    input rst,

    //data z Uart2wb 
    input [33:0] in_WB_ctr_w,
    input        in_WB_o_cyc,

    //data to wb2Uart
    output [33:0] out_WB2UART_word,
    output        out_WB2UART_cyc,


    //prikazi pri slavy
    inout [31:0]  io_wb_data,
    output [31:0] o_wb_addr,
    output        o_wb_we,  //write enable (write=1,read=0)
    output        o_wb_cyc,
    output        o_wb_stb,
  //  input         i_wb_stall, //tento signal bude pouzit pouze u asynchroni 
    input         i_wb_ack
);

//reg i_cmd_rd;       // prikaz je read
reg i_cmd_wr;       // prikaz je write
/* verilator lint_off UNUSED */
reg i_cmd_bus;      // prikaz je write nebo read
reg i_cmd_addr;     // prikaz je addresa
reg i_cmd_special;  // prikaz je specialni instrukce

wire w_cmd_addr;
wire w_cmd_write;
wire w_cmd_read;
wire w_cmd_bus;
wire [1:0] i_WB_cmd;


assign i_WB_cmd = in_WB_ctr_w[33:32];
assign w_cmd_addr  = (i_WB_cmd == 2)  ? 1 : 0;
assign w_cmd_write = (i_WB_cmd == 1)  ? 1 : 0;
assign w_cmd_read  = (i_WB_cmd == 0)  ? 1 : 0;
assign w_cmd_bus   = (i_WB_cmd[1]==0) ? 1 : 0;


always @(posedge clk)begin
    if(rst == 1) begin
       // i_cmd_rd <= 0;
        i_cmd_wr <= 0;
        i_cmd_bus <= 0;
        i_cmd_addr <= 0;
        i_cmd_special <= 0;
    end else begin
        if(in_WB_o_cyc == 1) begin
         //   if(i_WB_cmd == 0) i_cmd_rd <= 1;
         //   else i_cmd_rd <= 0;

            if(i_WB_cmd == 1) i_cmd_wr <= 1;
            else i_cmd_wr <= 0;

            if(i_WB_cmd == 2) i_cmd_addr <= 1;
            else i_cmd_addr <= 0;

            if(i_WB_cmd[1]==0) i_cmd_bus <= 1;
            else i_cmd_bus <= 0;
        end
    end
end

reg [31:0] ro_wb_addr;

always @(posedge clk) begin
    if(w_cmd_addr)
        ro_wb_addr <= in_WB_ctr_w[31:0];
end

assign o_wb_addr = ro_wb_addr;

/* verilator lint_off IMPLICIT */
reg r_cmd_bus_old;
reg r_cmd_bus;

always @(posedge clk) begin
    r_cmd_bus_old <= r_cmd_bus;
    r_cmd_bus <= in_WB_o_cyc;

end

assign w_cmd_bus_r = r_cmd_bus & ~r_cmd_bus_old;



reg ro_wb_cyc;
reg ro_wb_stb;
reg ro_wb_we;

reg [31:0] rio_wb_data;

always @(posedge clk)begin
    if(rst) begin
        ro_wb_cyc <= 0;
        ro_wb_stb <= 0;
    end else begin
        if(!ro_wb_cyc && !ro_wb_stb) begin
            if(w_cmd_bus_r)begin
                ro_wb_cyc <= 1;
                ro_wb_stb <= 1;
                ro_wb_we <= i_cmd_wr;
            end
        end else begin
            ro_wb_stb <= 0; //strobe se nastavuje vzdycky o periodu dele
            if(i_wb_ack) begin  //cyc az ve chvili kdy prijde ack
                ro_wb_cyc <= 0;
                ro_wb_we <= 0;
            end
        end
    end
end

always @(posedge clk) begin
    if(i_wb_ack && !w_cmd_write)   //i_cmd_mozna uz tou dobou bude v nule
        rio_wb_data <= io_wb_data;
    else
        rio_wb_data <= in_WB_ctr_w[31:0]; //todo nebo misto toho pouzit ro_wb_addr
end


reg [33:0] Rout_WB_ctr_r = 0;
reg Rout_WB2UART_cyc = 0;
always @(posedge clk) begin
    if(rst) begin
        Rout_WB_ctr_r <= 0;
        Rout_WB2UART_cyc <= 0;
    end else begin

        if((!o_wb_we) && (i_wb_ack)) begin
            Rout_WB_ctr_r[31:0] <= io_wb_data;
        end

        if(i_wb_ack) begin
            Rout_WB_ctr_r[33:32] <= i_WB_cmd;
            Rout_WB2UART_cyc <= 1;
        end
        else begin
            Rout_WB2UART_cyc <= 0;
        end


    end
end

assign out_WB2UART_word = Rout_WB_ctr_r;
assign out_WB2UART_cyc  = Rout_WB2UART_cyc;


assign o_wb_cyc = ro_wb_cyc;
assign o_wb_stb = ro_wb_stb;
assign o_wb_we = ro_wb_we;

assign io_wb_data = (ro_wb_we) ? rio_wb_data: 32'hZZZZ_ZZZZ;    // pri zapisu se posle hodnota regu, jinak vysoka impedance


endmodule

2023/lib/UART2WB/rtl/Uart2wb.sv
module Uart2wb 
(
    input clk,
    input rst,
    /* verilator lint_off UNUSED */
    input [7:0] UART_in_data,
    input UART_rx_done,
    output [33:0] WB_ctr_w,
    output WB_o_cyc
);

reg[4:0] asciiToBits;
reg UART_rx_done_1p;

always @(posedge clk) begin
    if (rst == 1) begin
    end else begin

        if(UART_rx_done)begin
            case (UART_in_data[6:0])
                7'h30: asciiToBits <= 5'h00;
                7'h31: asciiToBits <= 5'h01;
                7'h32: asciiToBits <= 5'h02;
                7'h33: asciiToBits <= 5'h03;
                7'h34: asciiToBits <= 5'h04;
                7'h35: asciiToBits <= 5'h05;
                7'h36: asciiToBits <= 5'h06;
                7'h37: asciiToBits <= 5'h07;
                7'h38: asciiToBits <= 5'h08;
                7'h39: asciiToBits <= 5'h09;
                7'h61: asciiToBits <= 5'h0a;
                7'h62: asciiToBits <= 5'h0b;
                7'h63: asciiToBits <= 5'h0c;
                7'h64: asciiToBits <= 5'h0d;
                7'h65: asciiToBits <= 5'h0e;
                7'h66: asciiToBits <= 5'h0f;
                7'h52: asciiToBits <= 5'h10; // R
                7'h57: asciiToBits <= 5'h11; // W
                7'h41: asciiToBits <= 5'h12; // A
                7'h53: asciiToBits <= 5'h13; // S - bude se jednat o reset
                7'h54: asciiToBits <= 5'h16; // T

            default:    //other character, are ignored
                        //nebo jako end of word character
                asciiToBits <= 5'h1f;
            endcase
        end

        UART_rx_done_1p <= UART_rx_done;
    end
end

reg [33:0] WB_ctr_w_r;
reg [33:0] WB_ctr_w_o;
reg WB_o_cyc_r;



always @(posedge clk) begin
    if(rst == 1) begin
    end else begin
        WB_o_cyc_r <= 0;
        if(UART_rx_done_1p) begin   //priznak, dalsiho pismene z uartu, zpozdene o jednu peridou
            if(asciiToBits[4] == 1) begin   //prikazy R,W,A,S,T
                WB_o_cyc_r <= 1;    //pokud jsou to prikazy, odeslat soucasne hodnoty ulozene v WB_ctr_w_r dále
                WB_ctr_w_o <= WB_ctr_w_r;
                WB_ctr_w_r[33:32] <= asciiToBits[1:0]; //ale tohle neplati pro T, todo!!!! 
                WB_ctr_w_r[31:0] <= 0;
            end else begin
                WB_ctr_w_r[31:0] <= {WB_ctr_w_r[27:0],asciiToBits[3:0]};  
            end
            
        end
    end
end

assign WB_o_cyc = WB_o_cyc_r;
assign WB_ctr_w = WB_ctr_w_o;


endmodule

2023/wbMaster/sim/top_WbMaster.sv
typedef enum logic [1:0] {
     add     = 2'h1,
     sub     = 2'h2,
     nop     = 2'h0
} operation_t /*verilator public*/;


module top_WbMaster
(
    input         clk,
    input         rst,

    input [7:0]   UART_in_data,
    input         UART_Rx_done,
    output [33:0] WB_ctr_w,
    output        WB_o_cyc,
    
    inout [31:0]  io_wb_data,
    output [31:0] o_wb_addr,
    output        o_wb_we,
    output        o_wb_cyc,
    output        o_wb_stb,
   // input       i_wb_stall,
    input         i_wb_ack,

    output [33:0] WB2UART_word,
    output        WB2UART_cyc,


    output UartTx_out

);

Uart2wb U2wb(
    .clk(clk),
    .rst(rst),
    .UART_in_data(UART_in_data),
    .UART_rx_done(UART_Rx_done),
    .WB_ctr_w(WB_ctr_w),
    .WB_o_cyc(WB_o_cyc)
);

WbMaster WBM (.clk(clk), 
              .rst(rst), 
              
              .in_WB_ctr_w(WB_ctr_w), 
              .in_WB_o_cyc(WB_o_cyc),

              .out_WB2UART_word(WB2UART_word),
              .out_WB2UART_cyc( WB2UART_cyc), 
              
              .io_wb_data(io_wb_data),
              .o_wb_addr(o_wb_addr),
              .o_wb_we(o_wb_we),
              .o_wb_cyc(o_wb_cyc),
              .o_wb_stb(o_wb_stb),
           //   .i_wb_stall(i_wb_stall),
              .i_wb_ack(i_wb_ack));

/* verilator lint_off UNUSED */
wire [7:0] U2Tx_DataByte;
wire       U2Tx_Start;
/* verilator lint_off UNDRIVEN */
reg       U2Tx_fComplete;


WB2UART wb2U(.clk(clk),
             .rst(rst),
             .in_WB2UART_word(WB2UART_word),
             .in_WB2UART_cyc(WB2UART_cyc),
             .out_DataByte(U2Tx_DataByte),
             .out_Start(U2Tx_Start),
             .in_fComplete(U2Tx_fComplete));

parameter KBA=5;
UartTx 
    #(.KBAUD(KBA))Utx
    (
        .clk(clk),
        .in_DataByte(U2Tx_DataByte),
        .in_Start(U2Tx_Start),
        .out_DataBit(UartTx_out),
        .out_fComplete(U2Tx_fComplete)
    );


endmodule

2023/wbMaster/sim/waveform.vcd
$version Generated by VerilatedVcd $end
$date Sun Oct 30 14:34:19 2022
 $end
$timescale   1ps $end

 $scope module TOP $end
  $var wire  1 F UART_Rx_done $end
  $var wire  8 E UART_in_data [7:0] $end
  $var wire  1 S UartTx_out $end
  $var wire  1 R WB2UART_cyc $end
  $var wire 34 P WB2UART_word [33:0] $end
  $var wire 34 G WB_ctr_w [33:0] $end
  $var wire  1 I WB_o_cyc $end
  $var wire  1 C clk $end
  $var wire  1 O i_wb_ack $end
  $var wire 32 J io_wb_data [31:0] $end
  $var wire 32 K o_wb_addr [31:0] $end
  $var wire  1 M o_wb_cyc $end
  $var wire  1 N o_wb_stb $end
  $var wire  1 L o_wb_we $end
  $var wire  1 D rst $end
  $scope module top_WbMaster $end
   $var wire 32 [ KBA [31:0] $end
   $var wire  8 Y U2Tx_DataByte [7:0] $end
   $var wire  1 Z U2Tx_Start $end
   $var wire  1 # U2Tx_fComplete $end
   $var wire  1 F UART_Rx_done $end
   $var wire  8 E UART_in_data [7:0] $end
   $var wire  1 S UartTx_out $end
   $var wire  1 R WB2UART_cyc $end
   $var wire 34 P WB2UART_word [33:0] $end
   $var wire 34 G WB_ctr_w [33:0] $end
   $var wire  1 I WB_o_cyc $end
   $var wire  1 C clk $end
   $var wire  1 O i_wb_ack $end
   $var wire 32 J io_wb_data [31:0] $end
   $var wire 32 K o_wb_addr [31:0] $end
   $var wire  1 M o_wb_cyc $end
   $var wire  1 N o_wb_stb $end
   $var wire  1 L o_wb_we $end
   $var wire  1 D rst $end
   $scope module U2wb $end
    $var wire  8 E UART_in_data [7:0] $end
    $var wire  1 F UART_rx_done $end
    $var wire  1 % UART_rx_done_1p $end
    $var wire 34 G WB_ctr_w [33:0] $end
    $var wire 34 ( WB_ctr_w_o [33:0] $end
    $var wire 34 & WB_ctr_w_r [33:0] $end
    $var wire  1 I WB_o_cyc $end
    $var wire  1 * WB_o_cyc_r $end
    $var wire  5 $ asciiToBits [4:0] $end
    $var wire  1 C clk $end
    $var wire  1 D rst $end
   $upscope $end
   $scope module Utx $end
    $var wire  8 @ Data [7:0] $end
    $var wire 32 [ KBAUD [31:0] $end
    $var wire  3 ? baud_cnt [2:0] $end
    $var wire  1 C clk $end
    $var wire  8 Y in_DataByte [7:0] $end
    $var wire  1 Z in_Start $end
    $var wire  1 S out_DataBit $end
    $var wire  1 # out_fComplete $end
    $var wire  4 A r_data_cnt [3:0] $end
    $var wire  1 B r_out_dataBit $end
    $var wire  1 # r_out_fComplete $end
    $var wire 32 ] s_DATA [31:0] $end
    $var wire 32 \ s_START [31:0] $end
    $var wire 32 ^ s_STOP [31:0] $end
    $var wire  2 > state [1:0] $end
   $upscope $end
   $scope module WBM $end
    $var wire  1 8 Rout_WB2UART_cyc $end
    $var wire 34 6 Rout_WB_ctr_r [33:0] $end
    $var wire  1 C clk $end
    $var wire  2 X i_WB_cmd [1:0] $end
    $var wire  1 - i_cmd_addr $end
    $var wire  1 , i_cmd_bus $end
    $var wire  1 . i_cmd_special $end
    $var wire  1 + i_cmd_wr $end
    $var wire  1 O i_wb_ack $end
    $var wire 34 G in_WB_ctr_w [33:0] $end
    $var wire  1 I in_WB_o_cyc $end
    $var wire 32 J io_wb_data [31:0] $end
    $var wire 32 K o_wb_addr [31:0] $end
    $var wire  1 M o_wb_cyc $end
    $var wire  1 N o_wb_stb $end
    $var wire  1 L o_wb_we $end
    $var wire  1 R out_WB2UART_cyc $end
    $var wire 34 P out_WB2UART_word [33:0] $end
    $var wire  1 1 r_cmd_bus $end
    $var wire  1 0 r_cmd_bus_old $end
    $var wire 32 5 rio_wb_data [31:0] $end
    $var wire 32 / ro_wb_addr [31:0] $end
    $var wire  1 2 ro_wb_cyc $end
    $var wire  1 3 ro_wb_stb $end
    $var wire  1 4 ro_wb_we $end
    $var wire  1 D rst $end
    $var wire  1 T w_cmd_addr $end
    $var wire  1 W w_cmd_bus $end
    $var wire  1 9 w_cmd_bus_r $end
    $var wire  1 V w_cmd_read $end
    $var wire  1 U w_cmd_write $end
   $upscope $end
   $scope module wb2U $end
    $var wire  1 C clk $end
    $var wire  1 R in_WB2UART_cyc $end
    $var wire 34 P in_WB2UART_word [33:0] $end
    $var wire  1 # in_fComplete $end
    $var wire  1 < in_fComplete_old $end
    $var wire  1 = in_fComplete_r $end
    $var wire  4 : index [3:0] $end
    $var wire  8 Y out_DataByte [7:0] $end
    $var wire  1 Z out_Start $end
    $var wire  1 D rst $end
    $var wire  1 ; ted $end
   $upscope $end
  $upscope $end
 $upscope $end
$enddefinitions $end


#0
0#
b00000 $
0%
b0000000000000000000000000000000000 &
b0000000000000000000000000000000000 (
0*
0+
0,
0-
0.
b00000000000000000000000000000000 /
00
01
02
03
04
b00000000000000000000000000000000 5
b0000000000000000000000000000000000 6
08
09
b0000 :
0;
0<
0=
b00 >
b000 ?
b00000000 @
b0000 A
0B
1C
1D
b00000000 E
0F
b0000000000000000000000000000000000 G
0I
b00000000000000000000000000000000 J
b00000000000000000000000000000000 K
0L
0M
0N
0O
b0000000000000000000000000000000000 P
0R
0S
0T
0U
1V
1W
b00 X
b00000000 Y
0Z
b00000000000000000000000000000101 [
b00000000000000000000000000000000 \
b00000000000000000000000000000001 ]
b00000000000000000000000000000010 ^
#1
0C
#2
1#
1=
1B
1C
1S
#3
0C
#4
0#
1<
0=
b01 >
b100 ?
0B
1C
0S
#5
0C
0D
#6
0<
b011 ?
1C
#7
0C
#8
b010 ?
1C
#9
0C
#10
b001 ?
1C
#11
0C
#12
b000 ?
1C
#13
0C
#14
b100 ?
b0001 A
1C
#15
0C
#16
b011 ?
1C
#17
0C
#18
b010 ?
1C
#19
0C
#20
b001 ?
1C
#21
0C
#22
b000 ?
1C
b00000000000000000000000000000101 J
1O
#23
0C
#24
b00000000000000000000000000000101 5
b0000000000000000000000000000000101 6
18
b100 ?
b0010 A
1C
b00000000000000000000000000000000 J
0O
b0000000000000000000000000000000101 P
1R
#25
0C
#26
b00000000000000000000000000000000 5
08
b1000 :
1;
b011 ?
1C
0R
#27
0C
#28
b0111 :
0;
b010 ?
1C
b01000001 E
1F
#29
0C
#30
b10010 $
1%
b001 ?
1C
0F
#31
0C
#32
0%
b1000000000000000000000000000000000 &
1*
b000 ?
1C
1I
#33
0C
#34
0*
1,
11
19
b100 ?
b0011 A
1C
0I
#35
0C
#36
10
01
12
13
09
b011 ?
1C
1M
1N
#37
0C
#38
00
03
b010 ?
1C
0N
#39
0C
#40
b001 ?
1C
b00110010 E
1F
b00000000000000000000000000000101 J
1O
#41
0C
#42
b00010 $
1%
02
b00000000000000000000000000000101 5
18
b000 ?
1C
0F
b00000000000000000000000000000000 J
0M
0O
1R
#43
0C
#44
0%
b1000000000000000000000000000000010 &
b00000000000000000000000000000000 5
08
b1000 :
1;
b100 ?
b0100 A
1C
0R
#45
0C
#46
b0111 :
0;
b011 ?
1C
#47
0C
#48
b010 ?
1C
#49
0C
#50
b001 ?
1C
#51
0C
#52
b000 ?
1C
b01010010 E
1F
#53
0C
#54
b10000 $
1%
b100 ?
b0101 A
1C
0F
#55
0C
#56
0%
b0000000000000000000000000000000000 &
b1000000000000000000000000000000010 (
1*
b011 ?
1C
b1000000000000000000000000000000010 G
1I
1T
0V
0W
b10 X
#57
0C
#58
0*
0,
1-
b00000000000000000000000000000010 /
11
b00000000000000000000000000000010 5
19
b010 ?
1C
0I
b00000000000000000000000000000010 K
#59
0C
#60
10
01
12
13
09
b001 ?
1C
1M
1N
#61
0C
#62
00
03
b000 ?
1C
0N
#63
0C
#64
b100 ?
b0110 A
1C
b01000001 E
1F
b00000000000000000000000000000101 J
1O
#65
0C
#66
b10010 $
1%
02
b00000000000000000000000000000101 5
b1000000000000000000000000000000101 6
18
b011 ?
1C
0F
b00000000000000000000000000000000 J
0M
0O
b1000000000000000000000000000000101 P
1R
#67
0C
#68
0%
b1000000000000000000000000000000000 &
b0000000000000000000000000000000000 (
1*
b00000000000000000000000000000010 5
08
b1000 :
1;
b010 ?
1C
b0000000000000000000000000000000000 G
1I
0R
0T
1V
1W
b00 X
#69
0C
#70
0*
1,
0-
11
b00000000000000000000000000000000 5
19
b0111 :
0;
b001 ?
1C
0I
#71
0C
#72
10
01
12
13
09
b000 ?
1C
1M
1N
#73
0C
#74
00
03
b100 ?
b0111 A
1C
0N
#75
0C
#76
b011 ?
1C
b00110100 E
1F
b00000000000000000000000000000101 J
1O
#77
0C
#78
b00100 $
1%
02
b00000000000000000000000000000101 5
b0000000000000000000000000000000101 6
18
b010 ?
1C
0F
b00000000000000000000000000000000 J
0M
0O
b0000000000000000000000000000000101 P
1R
#79
0C
#80
0%
b1000000000000000000000000000000100 &
b00000000000000000000000000000000 5
08
b1000 :
1;
b001 ?
1C
0R
#81
0C
#82
b0111 :
0;
b000 ?
1C
#83
0C
#84
b10 >
b100 ?
b1000 A
1C
#85
0C
#86
b011 ?
1C
#87
0C
#88
b010 ?
1C
b01010111 E
1F
#89
0C
#90
b10001 $
1%
b001 ?
1C
0F
#91
0C
#92
0%
b0100000000000000000000000000000000 &
b1000000000000000000000000000000100 (
1*
b000 ?
1C
b1000000000000000000000000000000100 G
1I
1T
0V
0W
b10 X
#93
0C
#94
0*
0,
1-
b00000000000000000000000000000100 /
11
b00000000000000000000000000000100 5
19
b00 >
b100 ?
1B
1C
0I
b00000000000000000000000000000100 K
1S
#95
0C
#96
10
01
12
13
09
b011 ?
1C
1M
1N
#97
0C
#98
00
03
b010 ?
1C
0N
#99
0C
#100
b001 ?
1C
b00110010 E
1F
b00000000000000000000000000000101 J
1O
#101
0C
#102
b00010 $
1%
02
b00000000000000000000000000000101 5
b1000000000000000000000000000000101 6
18
b000 ?
1C
0F
b00000000000000000000000000000000 J
0M
0O
b1000000000000000000000000000000101 P
1R
#103
0C
#104
1#
0%
b0100000000000000000000000000000010 &
b00000000000000000000000000000100 5
08
b1000 :
1;
1=
1C
0R
#105
0C
#106
0#
b0111 :
0;
1<
0=
b01 >
b100 ?
b0000 A
0B
1C
0S
#107
0C
#108
0<
b011 ?
1C
#109
0C
#110
b010 ?
1C
#111
0C
#112
b001 ?
1C
b01000001 E
1F
#113
0C
#114
b10010 $
1%
b000 ?
1C
0F
#115
0C
#116
0%
b1000000000000000000000000000000000 &
b0100000000000000000000000000000010 (
1*
b100 ?
b0001 A
1C
b0100000000000000000000000000000010 G
1I
0T
1U
1W
b01 X
#117
0C
#118
0*
1+
1,
0-
11
b00000000000000000000000000000010 5
19
b011 ?
1C
0I
#119
0C
#120
10
01
12
13
14
09
b010 ?
1C
b00000000000000000000000000000010 J
1L
1M
1N
#121
0C
#122
00
03
b001 ?
1C
0N
#123
0C
#124
b000 ?
1C
b00110001 E
1F
1O
#125
0C
#126
b00001 $
1%
02
04
b0100000000000000000000000000000101 6
18
b100 ?
b0010 A
1C
0F
b00000000000000000000000000000000 J
0L
0M
0O
b0100000000000000000000000000000101 P
1R
#127
0C
#128
0%
b1000000000000000000000000000000001 &
08
b1000 :
1;
b011 ?
1C
0R
#129
0C
#130
b0111 :
0;
b010 ?
1C
#131
0C
#132
b001 ?
1C
#133
0C
#134
b000 ?
1C
#135
0C
#136
b100 ?
b0011 A
1C
1F
#137
0C
#138
1%
b011 ?
1C
0F
#139
0C
#140
0%
b1000000000000000000000000000010001 &
b010 ?
1C
#141
0C
#142
b001 ?
1C
#143
0C
#144
b000 ?
1C
#145
0C
#146
b100 ?
b0100 A
1C
#147
0C
#148
b011 ?
1C
b00110010 E
1F
#149
0C
#150
b00010 $
1%
b010 ?
1C
0F
#151
0C
#152
0%
b1000000000000000000000000100010010 &
b001 ?
1C
#153
0C
#154
b000 ?
1C
#155
0C
#156
b100 ?
b0101 A
1C
#157
0C
#158
b011 ?
1C
#159
0C
#160
b010 ?
1C
b01010010 E
1F
#161
0C
#162
b10000 $
1%
b001 ?
1C
0F
#163
0C
#164
0%
b0000000000000000000000000000000000 &
b1000000000000000000000000100010010 (
1*
b000 ?
1C
b1000000000000000000000000100010010 G
1I
1T
0U
0W
b10 X
#165
0C
#166
0*
0+
0,
1-
b00000000000000000000000100010010 /
11
b00000000000000000000000100010010 5
19
b100 ?
b0110 A
1C
0I
b00000000000000000000000100010010 K
#167
0C
#168
10
01
12
13
09
b011 ?
1C
1M
1N
#169
0C
#170
00
03
b010 ?
1C
0N
#171
0C
#172
b001 ?
1C
b01000001 E
1F
b00000000000000000000000000000101 J
1O
#173
0C
#174
b10010 $
1%
02
b00000000000000000000000000000101 5
b1000000000000000000000000000000101 6
18
b000 ?
1C
0F
b00000000000000000000000000000000 J
0M
0O
b1000000000000000000000000000000101 P
1R
#175
0C
#176
0%
b1000000000000000000000000000000000 &
b0000000000000000000000000000000000 (
1*
b00000000000000000000000100010010 5
08
b1000 :
1;
b100 ?
b0111 A
1C
b0000000000000000000000000000000000 G
1I
0R
0T
1V
1W
b00 X
#177
0C
#178
0*
1,
0-
11
b00000000000000000000000000000000 5
19
b0111 :
0;
b011 ?
1C
0I
#179
0C
#180
10
01
12
13
09
b010 ?
1C
1M
1N
#181
0C
#182
00
03
b001 ?
1C
0N
#183
0C
#184
b000 ?
1C
b00110010 E
1F
b00000000000000000000000000000101 J
1O
#185
0C
#186
b00010 $
1%
02
b00000000000000000000000000000101 5
b0000000000000000000000000000000101 6
18
b10 >
b100 ?
b1000 A
1C
0F
b00000000000000000000000000000000 J
0M
0O
b0000000000000000000000000000000101 P
1R
#187
0C
#188
0%
b1000000000000000000000000000000010 &
b00000000000000000000000000000000 5
08
b1000 :
1;
b011 ?
1C
0R
#189
0C
#190
b0111 :
0;
b010 ?
1C
#191
0C
#192
b001 ?
1C
#193
0C
#194
b000 ?
1C
#195
0C
#196
b00 >
b100 ?
1B
1C
b01010010 E
1F
1S
#197
0C
#198
b10000 $
1%
b011 ?
1C
0F
#199
0C
#200
0%
b0000000000000000000000000000000000 &
b1000000000000000000000000000000010 (
1*
b010 ?
1C
b1000000000000000000000000000000010 G
1I
1T
0V
0W
b10 X
#201
0C
#202
0*
0,
1-
b00000000000000000000000000000010 /
11
b00000000000000000000000000000010 5
19
b001 ?
1C
0I
b00000000000000000000000000000010 K
#203
0C
#204
10
01
12
13
09
b000 ?
1C
1M
1N
#205
0C
#206
1#
00
03
1=
1C
0N
#207
0C
#208
0#
b0110 :
1<
0=
b01 >
b100 ?
b0000 A
0B
1C
b01000001 E
1F
b00000000000000000000000000000101 J
1O
0S
#209
0C
#210
b10010 $
1%
02
b00000000000000000000000000000101 5
b1000000000000000000000000000000101 6
18
0<
b011 ?
1C
0F
b00000000000000000000000000000000 J
0M
0O
b1000000000000000000000000000000101 P
1R
#211
0C
#212
0%
b1000000000000000000000000000000000 &
b0000000000000000000000000000000000 (
1*
b00000000000000000000000000000010 5
08
b1000 :
1;
b010 ?
1C
b0000000000000000000000000000000000 G
1I
0R
0T
1V
1W
b00 X
#213
0C
#214
0*
1,
0-
11
b00000000000000000000000000000000 5
19
b0111 :
0;
b001 ?
1C
0I
#215
0C
#216
10
01
12
13
09
b000 ?
1C
1M
1N
#217
0C
#218
00
03
b100 ?
b0001 A
1C
0N
#219
0C
#220
b011 ?
1C
b00110100 E
1F
b00000000000000000000000000000101 J
1O
#221
0C
#222
b00100 $
1%
02
b00000000000000000000000000000101 5
b0000000000000000000000000000000101 6
18
b010 ?
1C
0F
b00000000000000000000000000000000 J
0M
0O
b0000000000000000000000000000000101 P
1R
#223
0C
#224
0%
b1000000000000000000000000000000100 &
b00000000000000000000000000000000 5
08
b1000 :
1;
b001 ?
1C
0R
#225
0C
#226
b0111 :
0;
b000 ?
1C
#227
0C
#228
b100 ?
b0010 A
1C
#229
0C
#230
b011 ?
1C
#231
0C
#232
b010 ?
1C
b01010111 E
1F
#233
0C
#234
b10001 $
1%
b001 ?
1C
0F
#235
0C
#236
0%
b0100000000000000000000000000000000 &
b1000000000000000000000000000000100 (
1*
b000 ?
1C
b1000000000000000000000000000000100 G
1I
1T
0V
0W
b10 X
#237
0C
#238
0*
0,
1-
b00000000000000000000000000000100 /
11
b00000000000000000000000000000100 5
19
b100 ?
b0011 A
1C
0I
b00000000000000000000000000000100 K
#239
0C
#240
10
01
12
13
09
b011 ?
1C
1M
1N
#241
0C
#242
00
03
b010 ?
1C
0N
#243
0C
#244
b001 ?
1C
b00110010 E
1F
b00000000000000000000000000000101 J
1O
#245
0C
#246
b00010 $
1%
02
b00000000000000000000000000000101 5
b1000000000000000000000000000000101 6
18
b000 ?
1C
0F
b00000000000000000000000000000000 J
0M
0O
b1000000000000000000000000000000101 P
1R
#247
0C
#248
0%
b0100000000000000000000000000000010 &
b00000000000000000000000000000100 5
08
b1000 :
1;
b100 ?
b0100 A
1C
0R
#249
0C
#250
b0111 :
0;
b011 ?
1C
#251
0C
#252
b010 ?
1C
#253
0C
#254
b001 ?
1C
#255
0C
#256
b000 ?
1C
b01000001 E
1F
#257
0C
#258
b10010 $
1%
b100 ?
b0101 A
1C
0F
#259
0C
#260
0%
b1000000000000000000000000000000000 &
b0100000000000000000000000000000010 (
1*
b011 ?
1C
b0100000000000000000000000000000010 G
1I
0T
1U
1W
b01 X
#261
0C
#262
0*
1+
1,
0-
11
b00000000000000000000000000000010 5
19
b010 ?
1C
0I
#263
0C
#264
10
01
12
13
14
09
b001 ?
1C
b00000000000000000000000000000010 J
1L
1M
1N
#265
0C
#266
00
03
b000 ?
1C
0N
#267
0C
#268
b100 ?
b0110 A
1C
b00110001 E
1F
1O
#269
0C
#270
b00001 $
1%
02
04
b0100000000000000000000000000000101 6
18
b011 ?
1C
0F
b00000000000000000000000000000000 J
0L
0M
0O
b0100000000000000000000000000000101 P
1R
#271
0C
#272
0%
b1000000000000000000000000000000001 &
08
b1000 :
1;
b010 ?
1C
0R
#273
0C
#274
b0111 :
0;
b001 ?
1C
#275
0C
#276
b000 ?
1C
#277
0C
#278
b100 ?
b0111 A
1C
#279
0C
#280
b011 ?
1C
1F
#281
0C
#282
1%
b010 ?
1C
0F
#283
0C
#284
0%
b1000000000000000000000000000010001 &
b001 ?
1C
#285
0C
#286
b000 ?
1C
#287
0C
#288
b10 >
b100 ?
b1000 A
1C
#289
0C
#290
b011 ?
1C
#291
0C
#292
b010 ?
1C
b00110010 E
1F
#293
0C
#294
b00010 $
1%
b001 ?
1C
0F
#295
0C
#296
0%
b1000000000000000000000000100010010 &
b000 ?
1C
#297
0C
#298
b00 >
b100 ?
1B
1C
1S
#299
0C
