2023/lib/WB2UART/rtl/WB2UART.sv
module WB2UART
(
    input clk,
    input rst,
    
    //prikazy z mastera
    /* verilator lint_off UNUSED */
    input [33:0] in_WB2UART_word,
    input        in_WB2UART_cyc,
    output       out_WB2UART_stall, /*signál aktivního přenosu*/

    //prikazi pro UartTx transmitera (lib/UART/rtl/UartTx.sv)
    /* verilator lint_off UNDRIVEN */
    output [7:0] out_DataByte,  // pozadovane pismeno k odeslani
    output       out_Start,     // pozadavek pro odeslani dalsiho znaku
    input        in_fComplete   // pismeno bylo uspesne prenesene
);

reg[3:0] index;
reg ted;
reg in_fComplete_old;
wire in_fComplete_r;
reg r_fComplete_r_old;

reg [4:0] Rout_DataByte;
reg [31:0] regInWord;
reg test2;
reg rOut_Start;

reg r_WB2UART_stall;


always @(posedge clk) begin
    ted <= 0;
    test2 <= 0;
    rOut_Start <= 0;
    if((rst) || (in_WB2UART_word[33:32] == 3)) begin
        index <= 0;
        in_fComplete_old <= 0;
        regInWord <=0;
        r_WB2UART_stall <= 0;
        r_fComplete_r_old <= 0;

        
    end else begin
        if(in_WB2UART_cyc) begin
            index <= 8;     //1 řídící + 8 datovych znaků
            Rout_DataByte[4:4] <= 1;
            Rout_DataByte[0:0] <= in_WB2UART_word[32:32];
            Rout_DataByte[3:1] <= 0; 
            ted <= 1; 
            rOut_Start <= 1;
            r_WB2UART_stall <= 1;    
        end
    end

    if((in_fComplete_r) && (index > 0)) begin
        test2 <= 1;
        index <= index - 1;
        Rout_DataByte[4:4] <= 0;
        Rout_DataByte[3:0] <= regInWord[31:28];
        regInWord <= {regInWord[27:0],4'h0};
        rOut_Start <= 1;

    end

    if(index == 0 && (r_fComplete_r_old == 1)) begin
        r_WB2UART_stall <= 0;
    end

    in_fComplete_old <= in_fComplete;

    r_fComplete_r_old <= in_fComplete_r;
end

assign out_Start = rOut_Start;
assign out_WB2UART_stall = r_WB2UART_stall;

reg [6:0] out_DataByte2;

always @(ted or in_fComplete_r) begin
   // out_DataByte = 
    case(Rout_DataByte[4:0]) 
        5'h00: out_DataByte2 <= 7'h30;
        5'h01: out_DataByte2 <= 7'h31;
        5'h02: out_DataByte2 <= 7'h32;
        5'h03: out_DataByte2 <= 7'h33;
        5'h04: out_DataByte2 <= 7'h34;
        5'h05: out_DataByte2 <= 7'h35;
        5'h06: out_DataByte2 <= 7'h36;
        5'h07: out_DataByte2 <= 7'h37;
        5'h08: out_DataByte2 <= 7'h38;
        5'h09: out_DataByte2 <= 7'h39;
        5'h0a: out_DataByte2 <= 7'h61;
        5'h0b: out_DataByte2 <= 7'h62;
        5'h0c: out_DataByte2 <= 7'h63;
        5'h0d: out_DataByte2 <= 7'h64;
        5'h0e: out_DataByte2 <= 7'h65;
        5'h0f: out_DataByte2 <= 7'h66;

        5'h10: out_DataByte2 <= 7'h52;
        5'h11: out_DataByte2 <= 7'h57; 
default:
    out_DataByte2 <= 7'h14;
    endcase
end

assign out_DataByte[6:0] = out_DataByte2;





assign in_fComplete_r = in_fComplete & (~in_fComplete_old);
//assign out_DataByte = Rout_DataByte;

endmodule

2023/wbMaster/rtl/WbMaster.sv
module WbMaster
(
    input clk, 
    input rst,

    //data z Uart2wb 
    input [33:0] in_WB_ctr_w,
    input        in_WB_o_cyc,

    //data to wb2Uart
    output [33:0] out_WB2UART_word,
    output        out_WB2UART_cyc,


    //prikazi pro slaves
    inout [31:0]  io_wb_data,
    output [31:0] o_wb_addr,
    output        o_wb_we,  //write enable (write=1,read=0)
    output        o_wb_cyc,
    output        o_wb_stb,
  //  input         i_wb_stall, //tento signal bude pouzit pouze u asynchroni 
    input         i_wb_ack
);

//reg i_cmd_rd;       // prikaz je read
reg i_cmd_wr;       // prikaz je write
/* verilator lint_off UNUSED */
reg i_cmd_bus;      // prikaz je write nebo read
reg i_cmd_addr;     // prikaz je addresa
reg i_cmd_special;  // prikaz je specialni instrukce

wire w_cmd_addr;
wire w_cmd_write;
wire w_cmd_rst;
wire w_cmd_read;
wire w_cmd_bus;
wire [1:0] i_WB_cmd;


assign i_WB_cmd    = in_WB_ctr_w[33:32];
assign w_cmd_addr  = (i_WB_cmd == 2)  ? 1 : 0;
assign w_cmd_rst   = (i_WB_cmd == 3)  ? 1 : 0;
assign w_cmd_write = (i_WB_cmd == 1)  ? 1 : 0;
assign w_cmd_read  = (i_WB_cmd == 0)  ? 1 : 0;
assign w_cmd_bus   = (i_WB_cmd[1]==0) ? 1 : 0;


always @(posedge clk)begin
    if(rst == 1) begin
       // i_cmd_rd <= 0;
        i_cmd_wr <= 0;
        i_cmd_bus <= 0;
        i_cmd_addr <= 0;
        i_cmd_special <= 0;
    end else begin
        if(in_WB_o_cyc == 1) begin
         //   if(i_WB_cmd == 0) i_cmd_rd <= 1;
         //   else i_cmd_rd <= 0;

            if(i_WB_cmd == 1) i_cmd_wr <= 1;
            else i_cmd_wr <= 0;

            if(i_WB_cmd == 2) i_cmd_addr <= 1;
            else i_cmd_addr <= 0;

            if(i_WB_cmd[1]==0) i_cmd_bus <= 1;
            else i_cmd_bus <= 0;
        end
    end
end

reg [31:0] ro_wb_addr;

always @(posedge clk) begin
    if(w_cmd_addr)
        ro_wb_addr <= in_WB_ctr_w[31:0];
end

assign o_wb_addr = ro_wb_addr;

/* verilator lint_off IMPLICIT */
reg r_cmd_bus_old;
reg r_cmd_bus;

always @(posedge clk) begin
    r_cmd_bus_old <= r_cmd_bus;
    r_cmd_bus <= in_WB_o_cyc;

end

assign w_cmd_bus_r = r_cmd_bus & ~r_cmd_bus_old;



reg ro_wb_cyc;
reg ro_wb_stb;
reg ro_wb_we;

reg [31:0] rio_wb_data;

always @(posedge clk)begin

    if(rst) begin
        ro_wb_cyc <= 0;
        ro_wb_stb <= 0;
    end else begin
        if(!ro_wb_cyc && !ro_wb_stb) begin
            if(w_cmd_bus_r)begin
                ro_wb_cyc <= 1;
                ro_wb_stb <= 1;
                ro_wb_we <= i_cmd_wr;
            end
        end else begin
            ro_wb_stb <= 0; //strobe se nastavuje vzdycky o periodu dele,(nastavuje se pouze na jednu periodu)
            if(i_wb_ack) begin  //cyc az ve chvili kdy prijde ack
                ro_wb_cyc <= 0;
                ro_wb_we <= 0;
            end
        end 
    end //end reset

end //end always

always @(posedge clk) begin
    if(i_wb_ack && !w_cmd_write)   //i_cmd_mozna uz tou dobou bude v nule
        rio_wb_data <= io_wb_data;
    else
        rio_wb_data <= in_WB_ctr_w[31:0]; //todo nebo misto toho pouzit ro_wb_addr
end


reg [33:0] Rout_WB_ctr_r = 0;
reg Rout_WB2UART_cyc = 0;

//@brief - odelsani w/r pro wb2uart modul
always @(posedge clk) begin

    if(rst) begin
        Rout_WB_ctr_r <= 0;
        Rout_WB2UART_cyc <= 0;
    end else begin

        if(w_cmd_bus) begin //pokud je příkaz r/w

            if(i_wb_ack) begin
                if(!o_wb_we) begin
                    Rout_WB_ctr_r[31:0] <= io_wb_data;
                end else begin 
                    Rout_WB_ctr_r[31:0] <= 0;
                end
            end

            if(i_wb_ack) begin
                Rout_WB_ctr_r[33:32] <= i_WB_cmd;
                Rout_WB2UART_cyc <= 1;
            end else begin
                Rout_WB2UART_cyc <= 0;
            end
        end else if(w_cmd_rst) begin    //pokud je prikaz reset
            Rout_WB_ctr_r[33:32] <= 3;
            Rout_WB2UART_cyc <= 1;
        end else begin
            Rout_WB2UART_cyc <= 0;
        end       
    end //end !reset

end

assign out_WB2UART_word = Rout_WB_ctr_r;
assign out_WB2UART_cyc  = Rout_WB2UART_cyc;


assign o_wb_cyc = ro_wb_cyc;
assign o_wb_stb = ro_wb_stb;
assign o_wb_we = ro_wb_we;

assign io_wb_data = (ro_wb_we) ? rio_wb_data: 32'hZZZZ_ZZZZ;    // pri zapisu se posle hodnota regu, jinak vysoka impedance


endmodule

2023/lib/UART2WB/rtl/Uart2wb.sv
module Uart2wb 
(
    input clk,
    input rst,
    /* verilator lint_off UNUSED */
    input [7:0] UART_in_data,
    input UART_rx_done,
    output [33:0] WB_ctr_w,
    output WB_o_cyc
);

reg[4:0] asciiToBits;
reg UART_rx_done_1p;

always @(posedge clk) begin
    if (rst == 1) begin
    end else begin

        if(UART_rx_done)begin
            case (UART_in_data[6:0])
            7'h30: asciiToBits <= 5'h00;
            7'h31: asciiToBits <= 5'h01;
            7'h32: asciiToBits <= 5'h02;
            7'h33: asciiToBits <= 5'h03;
            7'h34: asciiToBits <= 5'h04;
            7'h35: asciiToBits <= 5'h05;
            7'h36: asciiToBits <= 5'h06;
            7'h37: asciiToBits <= 5'h07;
            7'h38: asciiToBits <= 5'h08;
            7'h39: asciiToBits <= 5'h09;
            7'h61: asciiToBits <= 5'h0a;
            7'h62: asciiToBits <= 5'h0b;
            7'h63: asciiToBits <= 5'h0c;
            7'h64: asciiToBits <= 5'h0d;
            7'h65: asciiToBits <= 5'h0e;
            7'h66: asciiToBits <= 5'h0f;
            7'h52: asciiToBits <= 5'h10; // R
            7'h57: asciiToBits <= 5'h11; // W
            7'h41: asciiToBits <= 5'h12; // A
            7'h53: asciiToBits <= 5'h13; // S - bude se jednat o reset
            7'h54: asciiToBits <= 5'h16; // T

            default:    //other character, are ignored
                        //nebo jako end of word character
                asciiToBits <= 5'h1f;
            endcase
        end

        UART_rx_done_1p <= UART_rx_done;
    end
end

reg [33:0] WB_ctr_w_r;
reg [33:0] WB_ctr_w_o;
reg WB_o_cyc_r;



always @(posedge clk) begin
    if(rst == 1) begin
    end else begin
        WB_o_cyc_r <= 0;
        if(UART_rx_done_1p) begin   //priznak, dalsiho pismene z uartu, zpozdene o jednu peridou
            if(asciiToBits[4] == 1) begin   //prikazy R,W,A,S,T
                WB_o_cyc_r <= 1;    //pokud jsou to prikazy, odeslat soucasne hodnoty ulozene v WB_ctr_w_r dále
                WB_ctr_w_o <= WB_ctr_w_r;
                WB_ctr_w_r[33:32] <= asciiToBits[1:0]; //ale tohle neplati pro T, todo!!!! 
                WB_ctr_w_r[31:0] <= 0;
            end else begin
                WB_ctr_w_r[31:0] <= {WB_ctr_w_r[27:0],asciiToBits[3:0]};  
            end
            
        end
    end
end

assign WB_o_cyc = WB_o_cyc_r;
assign WB_ctr_w = WB_ctr_w_o;


endmodule

2023/wbMaster/sim/top_WbMaster.sv
typedef enum logic [1:0] {
     add     = 2'h1,
     sub     = 2'h2,
     nop     = 2'h0
} operation_t /*verilator public*/;


module top_WbMaster
(
    input         clk,
    input         rst,

    input [7:0]   UART_in_data,
    input         UART_Rx_done,
    output [33:0] WB_ctr_w,
    output        WB_o_cyc,
    
    inout [31:0]  io_wb_data,
    output [31:0] o_wb_addr,
    output        o_wb_we,
    output        o_wb_cyc,
    output        o_wb_stb,
   // input       i_wb_stall,
    input         i_wb_ack,

    output        WB2UART_stall,

    output [33:0] WB2UART_word,
    output        WB2UART_cyc,


    //START DEBUG C++
    /* verilator lint_off UNUSEDSIGNAL */
    input [31:0] tst1,
    input [31:0] tst2,
    input [31:0] tst3,
    input [31:0] tst4,
    input [31:0] Rx_wait,
    input [31:0] wait_A_cnt,
    input [31:0] wait_cnt,
    input [31:0] cmd_index,
    //END DEBUG C++


    
    output U2Tx_Start,         //pozadavek na odeslani dalsiho znaku z WB2Uart do UartTx
    output [7:0] U2Tx_DataByte,
    input  U2Tx_fComplete       //signál z UartTx, úspěšný přenos znaku

);

Uart2wb U2wb(
    .clk(clk),
    .rst(rst),
    .UART_in_data(UART_in_data),
    .UART_rx_done(UART_Rx_done),
    .WB_ctr_w(WB_ctr_w),
    .WB_o_cyc(WB_o_cyc)
);

WbMaster WBM (.clk(clk), 
              .rst(rst), 
              
              .in_WB_ctr_w(WB_ctr_w), 
              .in_WB_o_cyc(WB_o_cyc),

              .out_WB2UART_word(WB2UART_word),
              .out_WB2UART_cyc(WB2UART_cyc), 
              
              .io_wb_data(io_wb_data),
              .o_wb_addr(o_wb_addr),
              .o_wb_we(o_wb_we),
              .o_wb_cyc(o_wb_cyc),
              .o_wb_stb(o_wb_stb),
           //   .i_wb_stall(i_wb_stall),
              .i_wb_ack(i_wb_ack));

/* verilator lint_off UNUSED */
//wire [7:0] U2Tx_DataByte;
//wire       U2Tx_Start;
/* verilator lint_off UNDRIVEN */
//reg       U2Tx_fComplete;


WB2UART wb2U(.clk(clk),
             .rst(rst),
             .in_WB2UART_word(WB2UART_word),
             .in_WB2UART_cyc(WB2UART_cyc),
             .out_WB2UART_stall(WB2UART_stall),
             .out_DataByte(U2Tx_DataByte),
             .out_Start(U2Tx_Start),
             .in_fComplete(U2Tx_fComplete));

parameter KBA=5;
/*UartTx #(.KBAUD(KBA))Utx
    (
        .clk(clk),
        .in_DataByte(U2Tx_DataByte),
        .in_Start(U2Tx_Start),
        .out_DataBit(UartTx_out),
        .out_fComplete(U2Tx_fComplete)
    );
*/

endmodule

2023/wbMaster/sim/waveform.vcd
$version Generated by VerilatedVcd $end
$date 11/25/22 20:07:53 $end
$timescale 1ps $end

 $scope module TOP $end
  $var wire 32 ] Rx_wait [31:0] $end
  $var wire  8 b U2Tx_DataByte [7:0] $end
  $var wire  1 a U2Tx_Start $end
  $var wire  1 c U2Tx_fComplete $end
  $var wire  1 K UART_Rx_done $end
  $var wire  8 J UART_in_data [7:0] $end
  $var wire  1 X WB2UART_cyc $end
  $var wire  1 U WB2UART_stall $end
  $var wire 34 V WB2UART_word [33:0] $end
  $var wire 34 L WB_ctr_w [33:0] $end
  $var wire  1 N WB_o_cyc $end
  $var wire  1 H clk $end
  $var wire 32 ` cmd_index [31:0] $end
  $var wire  1 T i_wb_ack $end
  $var wire 32 O io_wb_data [31:0] $end
  $var wire 32 P o_wb_addr [31:0] $end
  $var wire  1 R o_wb_cyc $end
  $var wire  1 S o_wb_stb $end
  $var wire  1 Q o_wb_we $end
  $var wire  1 I rst $end
  $var wire 32 Y tst1 [31:0] $end
  $var wire 32 Z tst2 [31:0] $end
  $var wire 32 [ tst3 [31:0] $end
  $var wire 32 \ tst4 [31:0] $end
  $var wire 32 ^ wait_A_cnt [31:0] $end
  $var wire 32 _ wait_cnt [31:0] $end
  $scope module top_WbMaster $end
   $var wire 32 f KBA [31:0] $end
   $var wire 32 ] Rx_wait [31:0] $end
   $var wire  8 b U2Tx_DataByte [7:0] $end
   $var wire  1 a U2Tx_Start $end
   $var wire  1 c U2Tx_fComplete $end
   $var wire  1 K UART_Rx_done $end
   $var wire  8 J UART_in_data [7:0] $end
   $var wire  1 X WB2UART_cyc $end
   $var wire  1 U WB2UART_stall $end
   $var wire 34 V WB2UART_word [33:0] $end
   $var wire 34 L WB_ctr_w [33:0] $end
   $var wire  1 N WB_o_cyc $end
   $var wire  1 H clk $end
   $var wire 32 ` cmd_index [31:0] $end
   $var wire  1 T i_wb_ack $end
   $var wire 32 O io_wb_data [31:0] $end
   $var wire 32 P o_wb_addr [31:0] $end
   $var wire  1 R o_wb_cyc $end
   $var wire  1 S o_wb_stb $end
   $var wire  1 Q o_wb_we $end
   $var wire  1 I rst $end
   $var wire 32 Y tst1 [31:0] $end
   $var wire 32 Z tst2 [31:0] $end
   $var wire 32 [ tst3 [31:0] $end
   $var wire 32 \ tst4 [31:0] $end
   $var wire 32 ^ wait_A_cnt [31:0] $end
   $var wire 32 _ wait_cnt [31:0] $end
   $scope module U2wb $end
    $var wire  8 J UART_in_data [7:0] $end
    $var wire  1 K UART_rx_done $end
    $var wire  1 $ UART_rx_done_1p $end
    $var wire 34 L WB_ctr_w [33:0] $end
    $var wire 34 ' WB_ctr_w_o [33:0] $end
    $var wire 34 % WB_ctr_w_r [33:0] $end
    $var wire  1 N WB_o_cyc $end
    $var wire  1 ) WB_o_cyc_r $end
    $var wire  5 # asciiToBits [4:0] $end
    $var wire  1 H clk $end
    $var wire  1 I rst $end
   $upscope $end
   $scope module WBM $end
    $var wire  1 > Rout_WB2UART_cyc $end
    $var wire 34 < Rout_WB_ctr_r [33:0] $end
    $var wire  1 H clk $end
    $var wire  2 3 i_WB_cmd [1:0] $end
    $var wire  1 , i_cmd_addr $end
    $var wire  1 + i_cmd_bus $end
    $var wire  1 - i_cmd_special $end
    $var wire  1 * i_cmd_wr $end
    $var wire  1 T i_wb_ack $end
    $var wire 34 L in_WB_ctr_w [33:0] $end
    $var wire  1 N in_WB_o_cyc $end
    $var wire 32 O io_wb_data [31:0] $end
    $var wire 32 P o_wb_addr [31:0] $end
    $var wire  1 R o_wb_cyc $end
    $var wire  1 S o_wb_stb $end
    $var wire  1 Q o_wb_we $end
    $var wire  1 X out_WB2UART_cyc $end
    $var wire 34 V out_WB2UART_word [33:0] $end
    $var wire  1 6 r_cmd_bus $end
    $var wire  1 5 r_cmd_bus_old $end
    $var wire 32 ; rio_wb_data [31:0] $end
    $var wire 32 4 ro_wb_addr [31:0] $end
    $var wire  1 8 ro_wb_cyc $end
    $var wire  1 9 ro_wb_stb $end
    $var wire  1 : ro_wb_we $end
    $var wire  1 I rst $end
    $var wire  1 . w_cmd_addr $end
    $var wire  1 2 w_cmd_bus $end
    $var wire  1 7 w_cmd_bus_r $end
    $var wire  1 1 w_cmd_read $end
    $var wire  1 0 w_cmd_rst $end
    $var wire  1 / w_cmd_write $end
   $upscope $end
   $scope module wb2U $end
    $var wire  5 C Rout_DataByte [4:0] $end
    $var wire  1 H clk $end
    $var wire  1 X in_WB2UART_cyc $end
    $var wire 34 V in_WB2UART_word [33:0] $end
    $var wire  1 c in_fComplete $end
    $var wire  1 @ in_fComplete_old $end
    $var wire  1 d in_fComplete_r $end
    $var wire  4 A index [3:0] $end
    $var wire  8 b out_DataByte [7:0] $end
    $var wire  7 e out_DataByte2 [6:0] $end
    $var wire  1 a out_Start $end
    $var wire  1 U out_WB2UART_stall $end
    $var wire  1 F rOut_Start $end
    $var wire  1 G r_WB2UART_stall $end
    $var wire  1 B r_fComplete_r_old $end
    $var wire 32 D regInWord [31:0] $end
    $var wire  1 I rst $end
    $var wire  1 ? ted $end
    $var wire  1 E test2 $end
   $upscope $end
  $upscope $end
 $upscope $end
$enddefinitions $end


#0
b00000 #
0$
b0000000000000000000000000000000000 %
b0000000000000000000000000000000000 '
0)
0*
0+
0,
0-
0.
0/
00
11
12
b00 3
b00000000000000000000000000000000 4
05
06
07
08
09
0:
b00000000000000000000000000000000 ;
b0000000000000000000000000000000000 <
0>
0?
0@
b0000 A
0B
b00000 C
b00000000000000000000000000000000 D
0E
0F
0G
1H
1I
b00000000 J
0K
b0000000000000000000000000000000000 L
0N
b00000000000000000000000000000000 O
b00000000000000000000000000000000 P
0Q
0R
0S
0T
0U
b0000000000000000000000000000000000 V
0X
b00000000000000000000000000000000 Y
b00000000000000000000000000000000 Z
b00000000000000000000000000000000 [
b00000000000000000000000000000000 \
b00000000000000000000000000000000 ]
b00000000000000000000000000000000 ^
b00000000000000000000000000000000 _
b00000000000000000000000000000000 `
0a
b00110000 b
0c
0d
b0110000 e
b00000000000000000000000000000101 f
#1
0H
#2
1H
#3
0H
#4
1H
#5
0H
0I
#6
1H
#7
0H
#8
1H
#9
0H
#10
1H
#11
0H
#12
1H
#13
0H
#14
1H
#15
0H
#16
1H
#17
0H
#18
1H
#19
0H
#20
1H
b01010011 J
1K
b00000000000000000000000001000001 ]
#21
0H
#22
b10011 #
1$
1H
0K
1T
b00000000000000000000000000001000 \
#23
0H
#24
0$
b1100000000000000000000000000000000 %
1)
1>
1H
1N
0T
1X
b00000000000000000000000000000111 \
#25
0H
#26
0)
1+
16
17
0>
1?
b1000 A
b10000 C
1F
1G
1H
0N
1U
0X
b00000000000000000000000000000110 \
1a
b01010010 b
b1010010 e
#27
0H
#28
15
06
07
18
19
0?
0F
1H
1R
1S
b00000000000000000000000000000101 \
0a
#29
0H
#30
05
09
1H
0S
b00000000000000000000000000000100 \
#31
0H
#32
1H
1T
b00000000000000000000000000000011 \
#33
0H
#34
08
1>
1H
0R
0T
1X
b00000000000000000000000000000010 \
#35
0H
#36
0>
1?
1F
1H
0X
b00000000000000000000000000000001 \
1a
#37
0H
#38
0?
0F
1H
1K
b00000000000000000000000000000000 \
0a
#39
0H
#40
1$
1H
0K
b00000000000000000000000000001000 \
#41
0H
#42
0$
b1100000000000000000000000000000000 '
1)
10
01
02
b11 3
1H
b1100000000000000000000000000000000 L
1N
b00000000000000000000000000000111 \
#43
0H
#44
0)
0+
16
17
b1100000000000000000000000000000000 <
1>
1H
0N
b1100000000000000000000000000000000 V
1X
b00000000000000000000000000000110 \
#45
0H
#46
15
06
07
18
19
b0000 A
0G
1H
1R
1S
0U
b00000000000000000000000000000101 \
#47
0H
#48
05
09
1H
0S
b00000000000000000000000000000100 \
#49
0H
#50
1H
1T
b00000000000000000000000000000011 \
#51
0H
#52
08
1H
0R
0T
b00000000000000000000000000000010 \
#53
0H
#54
1H
b00000000000000000000000000000001 \
#55
0H
#56
1H
1K
b00000000000000000000000000000000 \
#57
0H
#58
1$
1H
0K
b00000000000000000000000000001000 \
#59
0H
#60
0$
1)
1H
1N
b00000000000000000000000000000111 \
#61
0H
#62
0)
16
17
1H
0N
b00000000000000000000000000000110 \
#63
0H
#64
15
06
07
18
19
1H
1R
1S
b00000000000000000000000000000101 \
#65
0H
#66
05
09
1H
0S
b00000000000000000000000000000100 \
#67
0H
#68
1H
1T
b00000000000000000000000000000011 \
#69
0H
#70
08
1H
0R
0T
b00000000000000000000000000000010 \
#71
0H
#72
1H
b00000000000000000000000000000001 \
#73
0H
#74
1H
1K
b00000000000000000000000000000000 \
#75
0H
#76
1$
1H
0K
b00000000000000000000000000001000 \
#77
0H
#78
0$
1)
1H
1N
b00000000000000000000000000000111 \
#79
0H
#80
0)
16
17
1H
0N
b00000000000000000000000000000110 \
#81
0H
#82
15
06
07
18
19
1H
1R
1S
b00000000000000000000000000000101 \
#83
0H
#84
05
09
1H
0S
b00000000000000000000000000000100 \
#85
0H
#86
1H
1T
b00000000000000000000000000000011 \
#87
0H
#88
08
1H
0R
0T
b00000000000000000000000000000010 \
#89
0H
#90
1H
b00000000000000000000000000000001 \
#91
0H
#92
1H
1K
b00000000000000000000000000000000 \
#93
0H
#94
1$
1H
0K
b00000000000000000000000000001000 \
#95
0H
#96
0$
1)
1H
1N
b00000000000000000000000000000111 \
#97
0H
#98
0)
16
17
1H
0N
b00000000000000000000000000000110 \
#99
0H
#100
15
06
07
18
19
1H
1R
1S
b00000000000000000000000000000101 \
#101
0H
#102
05
09
1H
0S
b00000000000000000000000000000100 \
#103
0H
#104
1H
1T
b00000000000000000000000000000011 \
#105
0H
#106
08
1H
0R
0T
b00000000000000000000000000000010 \
#107
0H
#108
1H
b00000000000000000000000000000001 \
#109
0H
#110
1H
1K
b00000000000000000000000000000000 \
#111
0H
#112
1$
1H
0K
b00000000000000000000000000001000 \
#113
0H
#114
0$
1)
1H
1N
b00000000000000000000000000000111 \
#115
0H
#116
0)
16
17
1H
0N
b00000000000000000000000000000110 \
#117
0H
#118
15
06
07
18
19
1H
1R
1S
b00000000000000000000000000000101 \
#119
0H
#120
05
09
1H
0S
b00000000000000000000000000000100 \
#121
0H
#122
1H
1T
b00000000000000000000000000000011 \
#123
0H
#124
08
1H
0R
0T
b00000000000000000000000000000010 \
#125
0H
#126
1H
b00000000000000000000000000000001 \
#127
0H
#128
1H
b01000001 J
1K
b00000000000000000000000000000000 \
#129
0H
#130
b10010 #
1$
1H
0K
b00000000000000000000000000001000 \
b00000000000000000000000000110001 ]
b00000000000000000000000000000001 `
#131
0H
#132
0$
b1000000000000000000000000000000000 %
1)
1H
1N
b00000000000000000000000000000111 \
#133
0H
#134
0)
16
17
1H
0N
b00000000000000000000000000000110 \
#135
0H
#136
15
06
07
18
19
1H
1R
1S
b00000000000000000000000000000101 \
#137
0H
#138
05
09
1H
0S
b00000000000000000000000000000100 \
#139
0H
#140
1H
1T
b00000000000000000000000000000011 \
#141
0H
#142
08
1H
0R
0T
b00000000000000000000000000000010 \
#143
0H
#144
1H
b00000000000000000000000000000001 \
#145
0H
#146
1H
b00110001 J
1K
b00000000000000000000000000000000 \
#147
0H
#148
b00001 #
1$
1H
0K
b00000000000000000000000000001000 \
b00000000000000000000000000110000 ]
b00000000000000000000000000000010 `
#149
0H
#150
0$
b1000000000000000000000000000000001 %
1H
b00000000000000000000000000000111 \
#151
0H
#152
1H
b00000000000000000000000000000110 \
#153
0H
#154
1H
b00000000000000000000000000000101 \
#155
0H
#156
1H
b00000000000000000000000000000100 \
#157
0H
#158
1H
b00000000000000000000000000000011 \
#159
0H
#160
1H
b00000000000000000000000000000010 \
#161
0H
#162
1H
b00000000000000000000000000000001 \
#163
0H
#164
1H
b00110000 J
1K
b00000000000000000000000000000000 \
#165
0H
#166
b00000 #
1$
1H
0K
b00000000000000000000000000001000 \
b00000000000000000000000000000011 `
#167
0H
#168
0$
b1000000000000000000000000000010000 %
1H
b00000000000000000000000000000111 \
#169
0H
#170
1H
b00000000000000000000000000000110 \
#171
0H
#172
1H
b00000000000000000000000000000101 \
#173
0H
#174
1H
b00000000000000000000000000000100 \
#175
0H
#176
1H
b00000000000000000000000000000011 \
#177
0H
#178
1H
b00000000000000000000000000000010 \
#179
0H
#180
1H
b00000000000000000000000000000001 \
#181
0H
#182
1H
1K
b00000000000000000000000000000000 \
#183
0H
#184
1$
1H
0K
b00000000000000000000000000001000 \
b00000000000000000000000000000100 `
#185
0H
#186
0$
b1000000000000000000000000100000000 %
1H
b00000000000000000000000000000111 \
#187
0H
#188
1H
b00000000000000000000000000000110 \
#189
0H
#190
1H
b00000000000000000000000000000101 \
#191
0H
#192
1H
b00000000000000000000000000000100 \
#193
0H
#194
1H
b00000000000000000000000000000011 \
#195
0H
#196
1H
b00000000000000000000000000000010 \
#197
0H
#198
1H
b00000000000000000000000000000001 \
#199
0H
#200
1H
1K
b00000000000000000000000000000000 \
#201
0H
#202
1$
1H
0K
b00000000000000000000000000001000 \
b00000000000000000000000000000101 `
#203
0H
#204
0$
b1000000000000000000001000000000000 %
1H
b00000000000000000000000000000111 \
#205
0H
#206
1H
b00000000000000000000000000000110 \
#207
0H
#208
1H
b00000000000000000000000000000101 \
#209
0H
#210
1H
b00000000000000000000000000000100 \
#211
0H
#212
1H
b00000000000000000000000000000011 \
#213
0H
#214
1H
b00000000000000000000000000000010 \
#215
0H
#216
1H
b00000000000000000000000000000001 \
#217
0H
#218
1H
1K
b00000000000000000000000000000000 \
#219
0H
#220
1$
1H
0K
b00000000000000000000000000001000 \
b00000000000000000000000001010111 ]
b00000000000000000000000000000110 `
#221
0H
#222
0$
b1000000000000000010000000000000000 %
1H
b00000000000000000000000000000111 \
#223
0H
#224
1H
b00000000000000000000000000000110 \
#225
0H
#226
1H
b00000000000000000000000000000101 \
#227
0H
#228
1H
b00000000000000000000000000000100 \
#229
0H
#230
1H
b00000000000000000000000000000011 \
#231
0H
#232
1H
b00000000000000000000000000000010 \
#233
0H
#234
1H
b00000000000000000000000000000001 \
#235
0H
#236
1H
b01010111 J
1K
b00000000000000000000000000000000 \
#237
0H
#238
b10001 #
1$
1H
0K
b00000000000000000000000000001000 \
b00000000000000000000000000110101 ]
b00000000000000000000000000000001 _
b00000000000000000000000000000111 `
#239
0H
#240
0$
b0100000000000000000000000000000000 %
b1000000000000000010000000000000000 '
1)
1.
00
b10 3
1H
b1000000000000000010000000000000000 L
1N
b00000000000000000000000000000111 \
#241
0H
#242
0)
1,
b00000000000000010000000000000000 4
16
17
b00000000000000010000000000000000 ;
0>
1H
0N
b00000000000000010000000000000000 P
0X
b00000000000000000000000000000110 \
#243
0H
#244
15
06
07
18
19
1H
1R
1S
b00000000000000000000000000000101 \
#245
0H
#246
05
09
1H
0S
b00000000000000000000000000000100 \
#247
0H
#248
1H
b00000000000000010000000000000000 O
1T
b00000000000000000000000000000011 \
#249
0H
#250
08
1H
b00000000000000000000000000000000 O
0R
0T
b00000000000000000000000000000010 \
#251
0H
#252
1H
b00000000000000000000000000000001 \
#253
0H
#254
1H
b00110101 J
1K
b00000000000000000000000000000000 \
#255
0H
#256
b00101 #
1$
1H
0K
b00000000000000000000000000001000 \
b00000000000000000000000001010010 ]
b00000000000000000000000000001000 `
#257
0H
#258
0$
b0100000000000000000000000000000101 %
1H
b00000000000000000000000000000111 \
#259
0H
#260
1H
b00000000000000000000000000000110 \
#261
0H
#262
1H
b00000000000000000000000000000101 \
#263
0H
#264
1H
b00000000000000000000000000000100 \
#265
0H
#266
1H
b00000000000000000000000000000011 \
#267
0H
#268
1H
b00000000000000000000000000000010 \
#269
0H
#270
1H
b00000000000000000000000000000001 \
#271
0H
#272
1H
b01010010 J
1K
b00000000000000000000000000000000 \
#273
0H
#274
b10000 #
1$
1H
0K
b00000000000000000000000000000001 [
b00000000000000000000000000001000 \
b00000000000000000000000001010111 ]
b00000000000000000000000000000010 _
b00000000000000000000000000001001 `
#275
0H
#276
0$
b0000000000000000000000000000000000 %
b0100000000000000000000000000000101 '
1)
0.
1/
12
b01 3
1H
b0100000000000000000000000000000101 L
1N
b00000000000000000000000000000111 \
#277
0H
#278
0)
1*
1+
0,
16
17
b00000000000000000000000000000101 ;
1H
0N
b00000000000000000000000000000110 \
#279
0H
#280
15
06
07
18
19
1:
1H
b00000000000000000000000000000101 O
1Q
1R
1S
b00000000000000000000000000000101 \
#281
0H
#282
05
09
1H
0S
b00000000000000000000000000000100 \
#283
0H
#284
1H
1T
b00000000000000000000000000000011 \
#285
0H
#286
08
0:
b0100000000000000000000000000000000 <
1>
1H
b00000000000000000000000000000000 O
0Q
0R
0T
b0100000000000000000000000000000000 V
1X
b00000000000000000000000000000010 \
#287
0H
#288
0>
1?
b1000 A
b10001 C
1F
1G
1H
1U
0X
b00000000000000000000000000000001 \
1a
b01010111 b
b1010111 e
#289
0H
#290
0?
0F
1H
b00000000000000000000000000000000 \
0a
