2023/lib/WB2UART/rtl/WB2UART.sv
module WB2UART
(
    input clk,
    input rst,
    
    //prikazy z mastera
    /* verilator lint_off UNUSED */
    input [33:0] in_WB2UART_word,
    input        in_WB2UART_cyc,
    output       out_WB2UART_stall, /*signál aktivního přenosu*/

    //prikazi pro UartTx transmitera (lib/UART/rtl/UartTx.sv)
    /* verilator lint_off UNDRIVEN */
    output [7:0] out_DataByte,  // pozadovane pismeno k odeslani
    output       out_Start,     // pozadavek pro odeslani dalsiho znaku
    input        in_fComplete   // pismeno bylo uspesne prenesene
);

reg[3:0] index;
reg ted;
reg in_fComplete_old;
wire in_fComplete_r;
reg r_fComplete_r_old;

reg [4:0] Rout_DataByte;
reg [31:0] regInWord;
reg test2;
reg rOut_Start;

reg r_WB2UART_stall;


always @(posedge clk) begin
    ted <= 0;
    test2 <= 0;
    rOut_Start <= 0;
    if((rst) || (in_WB2UART_word[33:32] == 3)) begin
        index <= 0;
        in_fComplete_old <= 0;
        regInWord <=0;
        r_WB2UART_stall <= 0;
        r_fComplete_r_old <= 0;

        
    end else begin
        if(in_WB2UART_cyc) begin
            index <= 8;     //1 řídící + 8 datovych znaků
            Rout_DataByte[4:4] <= 1;
            Rout_DataByte[0:0] <= in_WB2UART_word[32:32];
            Rout_DataByte[3:1] <= 0; 
            ted <= 1; 
            rOut_Start <= 1;
            r_WB2UART_stall <= 1;    
        end
    end

    if((in_fComplete_r) && (index > 0)) begin
        test2 <= 1;
        index <= index - 1;
        Rout_DataByte[4:4] <= 0;
        Rout_DataByte[3:0] <= regInWord[31:28];
        regInWord <= {regInWord[27:0],4'h0};
        rOut_Start <= 1;

    end

    if(index == 0 && (r_fComplete_r_old == 1)) begin
        r_WB2UART_stall <= 0;
    end

    in_fComplete_old <= in_fComplete;

    r_fComplete_r_old <= in_fComplete_r;
end

assign out_Start = rOut_Start;
assign out_WB2UART_stall = r_WB2UART_stall;

reg [6:0] out_DataByte2;

always @(ted or in_fComplete_r) begin
   // out_DataByte = 
    case(Rout_DataByte[4:0]) 
        5'h00: out_DataByte2 <= 7'h30;
        5'h01: out_DataByte2 <= 7'h31;
        5'h02: out_DataByte2 <= 7'h32;
        5'h03: out_DataByte2 <= 7'h33;
        5'h04: out_DataByte2 <= 7'h34;
        5'h05: out_DataByte2 <= 7'h35;
        5'h06: out_DataByte2 <= 7'h36;
        5'h07: out_DataByte2 <= 7'h37;
        5'h08: out_DataByte2 <= 7'h38;
        5'h09: out_DataByte2 <= 7'h39;
        5'h0a: out_DataByte2 <= 7'h61;
        5'h0b: out_DataByte2 <= 7'h62;
        5'h0c: out_DataByte2 <= 7'h63;
        5'h0d: out_DataByte2 <= 7'h64;
        5'h0e: out_DataByte2 <= 7'h65;
        5'h0f: out_DataByte2 <= 7'h66;

        5'h10: out_DataByte2 <= 7'h52;
        5'h11: out_DataByte2 <= 7'h57; 
default:
    out_DataByte2 <= 7'h14;
    endcase
end

assign out_DataByte[6:0] = out_DataByte2;





assign in_fComplete_r = in_fComplete & (~in_fComplete_old);
//assign out_DataByte = Rout_DataByte;

endmodule

2023/wbMaster/rtl/WbMaster.sv
module WbMaster
(
    input clk, 
    input rst,

    //data z Uart2wb 
    input [33:0] in_WB_ctr_w,
    input        in_WB_o_cyc,

    //data to wb2Uart
    output [33:0] out_WB2UART_word,
    output        out_WB2UART_cyc,


    //prikazi pro slaves
    inout [31:0]  io_wb_data,
    output [31:0] o_wb_addr,    // adresa pro slaves
    output        o_wb_we,  //write enable (write=1,read=0)
    output        o_wb_cyc,
    output        o_wb_stb,
  //  input         i_wb_stall, //tento signal bude pouzit pouze u asynchroni 
    input         i_wb_ack      // aknowledge from slave, that are valid data
);

//reg i_cmd_rd;       // prikaz je read
reg i_cmd_wr;       // prikaz je write
/* verilator lint_off UNUSED */
reg i_cmd_bus;      // prikaz je write nebo read
reg i_cmd_addr;     // prikaz je addresa
reg i_cmd_special;  // prikaz je specialni instrukce

wire w_cmd_addr;
wire w_cmd_write;
wire w_cmd_rst;
wire w_cmd_read;
wire w_cmd_bus;
wire [1:0] i_WB_cmd;


assign i_WB_cmd    = in_WB_ctr_w[33:32];
assign w_cmd_addr  = (i_WB_cmd == 2)  ? 1 : 0;
assign w_cmd_rst   = (i_WB_cmd == 3)  ? 1 : 0;
assign w_cmd_write = (i_WB_cmd == 1)  ? 1 : 0;
assign w_cmd_read  = (i_WB_cmd == 0)  ? 1 : 0;
assign w_cmd_bus   = (i_WB_cmd[1]==0) ? 1 : 0;


always @(posedge clk)begin
    if(rst == 1) begin
       // i_cmd_rd <= 0;
        i_cmd_wr <= 0;
        i_cmd_bus <= 0;
        i_cmd_addr <= 0;
        i_cmd_special <= 0;
    end else begin
        if(in_WB_o_cyc == 1) begin
         //   if(i_WB_cmd == 0) i_cmd_rd <= 1;
         //   else i_cmd_rd <= 0;

            if(i_WB_cmd == 1) i_cmd_wr <= 1;
            else i_cmd_wr <= 0;

            if(i_WB_cmd == 2) i_cmd_addr <= 1;
            else i_cmd_addr <= 0;

            if(i_WB_cmd[1]==0) i_cmd_bus <= 1;
            else i_cmd_bus <= 0;
        end
    end
end

reg [31:0] ro_wb_addr;

always @(posedge clk) begin
    if(w_cmd_addr)
        ro_wb_addr <= in_WB_ctr_w[31:0];
end

assign o_wb_addr = ro_wb_addr;

/* verilator lint_off IMPLICIT */
reg r_cmd_bus_old;
reg r_cmd_bus;

always @(posedge clk) begin
    r_cmd_bus_old <= r_cmd_bus;
    r_cmd_bus <= in_WB_o_cyc;
end

assign w_cmd_bus_r = r_cmd_bus & ~r_cmd_bus_old;

reg ro_wb_cyc;
reg ro_wb_stb;
reg ro_wb_we;

reg [31:0] rio_wb_data;

always @(posedge clk)begin

    if(rst) begin
        ro_wb_cyc <= 0;
        ro_wb_stb <= 0;
    end else begin
        if(!w_cmd_addr) begin
            if(!ro_wb_cyc && !ro_wb_stb) begin
                if(w_cmd_bus_r)begin
                    ro_wb_cyc <= 1;
                    ro_wb_stb <= 1;
                    ro_wb_we <= i_cmd_wr;
                end
            end else begin
                ro_wb_stb <= 0; //strobe se nastavuje vzdycky o periodu dele,(nastavuje se pouze na jednu periodu)
                if(i_wb_ack) begin  //cyc az ve chvili kdy prijde ack
                    ro_wb_cyc <= 0;
                    ro_wb_we <= 0;
                end
            end 
        end
    end //end reset

end //end always

always @(posedge clk) begin
    if(i_wb_ack && !w_cmd_write)   //i_cmd_mozna uz tou dobou bude v nule
        rio_wb_data <= io_wb_data;
    else
        rio_wb_data <= in_WB_ctr_w[31:0]; //todo nebo misto toho pouzit ro_wb_addr
end


reg [33:0] Rout_WB_ctr_r = 0;
reg Rout_WB2UART_cyc = 0;

//@brief - odelsani w/r pro wb2uart modul
always @(posedge clk) begin

    if(rst) begin
        Rout_WB_ctr_r <= 0;
        Rout_WB2UART_cyc <= 0;
    end else begin

        if(w_cmd_bus) begin //pokud je příkaz r/w

            if(i_wb_ack) begin
                if(!o_wb_we) begin
                    Rout_WB_ctr_r[31:0] <= io_wb_data;
                end else begin 
                    Rout_WB_ctr_r[31:0] <= 0;
                end
            end

            if(i_wb_ack) begin
                Rout_WB_ctr_r[33:32] <= i_WB_cmd;
                Rout_WB2UART_cyc <= 1;
            end else begin
                Rout_WB2UART_cyc <= 0;
            end
        end else if(w_cmd_rst) begin    //pokud je prikaz reset
            Rout_WB_ctr_r[33:32] <= 3;
            Rout_WB2UART_cyc <= 1;
        end else begin
            Rout_WB2UART_cyc <= 0;
        end       
    end //end !reset

end

assign out_WB2UART_word = Rout_WB_ctr_r;
assign out_WB2UART_cyc  = Rout_WB2UART_cyc;


assign o_wb_cyc = ro_wb_cyc;
assign o_wb_stb = ro_wb_stb;
assign o_wb_we = ro_wb_we;

assign io_wb_data = (ro_wb_we) ? rio_wb_data: 32'hZZZZ_ZZZZ;    // pri zapisu se posle hodnota regu, jinak vysoka impedance


endmodule

2023/lib/WB_MEMORY/rtl/wb_memory.sv


module wb_memory
(
    input clk,
    input rst,

    input i_wb_we,  // write enable 
    input i_wb_cyc, // jde do nuly az o jednu periodu dele
    input i_wb_stb, //stb jde do nuly hned potom

    output o_wb_ack, //potvrzeni od tohoto

    inout [31 : 0] io_wb_data,
    input [31 : 0] i_wb_addr
);


reg read_enable;
reg ro_wb_ack;
reg[31:0] memory [0:63];

reg [31:0] rout_wb_data;



initial begin
    memory[0] = 1;
    memory[1] = 262144;
    memory[50] = 500;
end

always @(posedge clk) begin
    if(rst == 1)begin
        rout_wb_data <= 0;
        read_enable <= 0;
        ro_wb_ack <= 0;
    end else begin
        if(i_wb_stb && i_wb_cyc && (i_wb_addr < 255)) begin
            if(i_wb_we) begin   //tady znamena cteni
                memory[i_wb_addr[5:0]] <= io_wb_data;
            end else begin
                rout_wb_data <= memory[i_wb_addr[5:0]];
            end

            if((i_wb_addr[31:6] < 255)) begin
                if(!i_wb_we) begin
                    read_enable <= 1;
                end
                ro_wb_ack <= 1;
            end else begin
                read_enable <= 0;
                ro_wb_ack <= 0;
            end



        end else if(ro_wb_ack) begin
            ro_wb_ack <= 0;
            read_enable <= 0;   
        end
    end 
end

assign o_wb_ack = ro_wb_ack;
assign io_wb_data = (read_enable) ? rout_wb_data : 32'hZZZZ_ZZZZ;



endmodule

2023/lib/UART2WB/rtl/Uart2wb.sv
module Uart2wb 
(
    input clk,
    input rst,
    /* verilator lint_off UNUSED */
    input [7:0] UART_in_data,
    input UART_rx_done,
    output [33:0] WB_ctr_w,
    output WB_o_cyc
);

reg[4:0] asciiToBits;
reg UART_rx_done_1p;

always @(posedge clk) begin
    if (rst == 1) begin
    end else begin

        if(UART_rx_done)begin
            case (UART_in_data[6:0])
                7'h30: asciiToBits <= 5'h00;
                7'h31: asciiToBits <= 5'h01;
                7'h32: asciiToBits <= 5'h02;
                7'h33: asciiToBits <= 5'h03;
                7'h34: asciiToBits <= 5'h04;
                7'h35: asciiToBits <= 5'h05;
                7'h36: asciiToBits <= 5'h06;
                7'h37: asciiToBits <= 5'h07;
                7'h38: asciiToBits <= 5'h08;
                7'h39: asciiToBits <= 5'h09;
                7'h61: asciiToBits <= 5'h0a;
                7'h62: asciiToBits <= 5'h0b;
                7'h63: asciiToBits <= 5'h0c;
                7'h64: asciiToBits <= 5'h0d;
                7'h65: asciiToBits <= 5'h0e;
                7'h66: asciiToBits <= 5'h0f;
                7'h52: asciiToBits <= 5'h10; // R
                7'h57: asciiToBits <= 5'h11; // W
                7'h41: asciiToBits <= 5'h12; // A
                7'h53: asciiToBits <= 5'h13; // S - bude se jednat o reset
                7'h54: asciiToBits <= 5'h16; // T

            default:    //other character, are ignored
                        //nebo jako end of word character
                asciiToBits <= 5'h1f;
            endcase
        end

        UART_rx_done_1p <= UART_rx_done;
    end
end

reg [33:0] WB_ctr_w_r;
reg [33:0] WB_ctr_w_o;
reg WB_o_cyc_r;



always @(posedge clk) begin
    if(rst == 1) begin
    end else begin
        WB_o_cyc_r <= 0;
        if(UART_rx_done_1p) begin   //priznak, dalsiho pismene z uartu, zpozdene o jednu peridou
            if(asciiToBits[4] == 1) begin   //prikazy R,W,A,S,T
                WB_o_cyc_r <= 1;    //pokud jsou to prikazy, odeslat soucasne hodnoty ulozene v WB_ctr_w_r dále
                WB_ctr_w_o <= WB_ctr_w_r;
                WB_ctr_w_r[33:32] <= asciiToBits[1:0]; //ale tohle neplati pro T, todo!!!! 
                WB_ctr_w_r[31:0] <= 0;
            end else begin
                WB_ctr_w_r[31:0] <= {WB_ctr_w_r[27:0],asciiToBits[3:0]};  
            end
            
        end
    end
end

assign WB_o_cyc = WB_o_cyc_r;
assign WB_ctr_w = WB_ctr_w_o;


endmodule

2023/wbMaster/sim/top_WbMaster.sv
typedef enum logic [1:0] {
     add     = 2'h1,
     sub     = 2'h2,
     nop     = 2'h0
} operation_t /*verilator public*/;


module top_WbMaster
(
    input         clk,
    input         rst,

    input [7:0]   UART_in_data,
    input         UART_Rx_done,
    output [33:0] WB_ctr_w,
    output        WB_o_cyc,
    
    inout [31:0]  io_wb_data,
    output [31:0] o_wb_addr,  // adresa pro slaves
    output        o_wb_we,
    output        o_wb_cyc,
    output        o_wb_stb,
`ifdef SLAVE_SIM 
    input         i_wb_ack,
`endif

    output        WB2UART_stall,

    output [33:0] WB2UART_word,
    output        WB2UART_cyc,


    //START DEBUG C++
    /* verilator lint_off UNUSEDSIGNAL */
    input [31:0] tst1,
    input [31:0] tst2,
    input [31:0] tst3,
    input [31:0] tst4,
    input [31:0] Rx_wait,
    input [31:0] wait_A_cnt,
    input [31:0] wait_cnt,
    input [31:0] cmd_index,
    input [31:0] slave_adresa,
    //END DEBUG C++


    
    output U2Tx_Start,         //pozadavek na odeslani dalsiho znaku z WB2Uart do UartTx
    output [7:0] U2Tx_DataByte,
    input  U2Tx_fComplete       //signál z UartTx, úspěšný přenos znaku

);



Uart2wb U2wb(
    .clk(clk),
    .rst(rst),
    .UART_in_data(UART_in_data),
    .UART_rx_done(UART_Rx_done),
    .WB_ctr_w(WB_ctr_w),
    .WB_o_cyc(WB_o_cyc)
);




`ifndef SLAVE_SIM
wire i_wb_ack;
wb_memory WBmemory
(
    .clk(clk),
    .rst(rst),

    .i_wb_we(o_wb_we),  // write enable 
    .i_wb_cyc(o_wb_cyc), // jde do nuly az o jednu periodu dele
    .i_wb_stb(o_wb_stb), //stb jde do nuly hned potom

    .o_wb_ack(i_wb_ack), //potvrzeni od tohoto
    
    .io_wb_data(io_wb_data),
    .i_wb_addr(o_wb_addr)

);

`endif




WbMaster WBM (.clk(clk), 
              .rst(rst), 
              
              .in_WB_ctr_w(WB_ctr_w), 
              .in_WB_o_cyc(WB_o_cyc),

              .out_WB2UART_word(WB2UART_word),
              .out_WB2UART_cyc(WB2UART_cyc), 
              
              .io_wb_data(io_wb_data),
              .o_wb_addr(o_wb_addr),
              .o_wb_we(o_wb_we),
              .o_wb_cyc(o_wb_cyc),
              .o_wb_stb(o_wb_stb),
           //   .i_wb_stall(i_wb_stall),
              .i_wb_ack(i_wb_ack));






/* verilator lint_off UNUSED */
//wire [7:0] U2Tx_DataByte;
//wire       U2Tx_Start;
/* verilator lint_off UNDRIVEN */
//reg       U2Tx_fComplete;


WB2UART wb2U(.clk(clk),
             .rst(rst),
             .in_WB2UART_word(WB2UART_word),
             .in_WB2UART_cyc(WB2UART_cyc),
             .out_WB2UART_stall(WB2UART_stall),
             .out_DataByte(U2Tx_DataByte),
             .out_Start(U2Tx_Start),
             .in_fComplete(U2Tx_fComplete));

parameter KBA=5;
/*UartTx #(.KBAUD(KBA))Utx
    (
        .clk(clk),
        .in_DataByte(U2Tx_DataByte),
        .in_Start(U2Tx_Start),
        .out_DataBit(UartTx_out),
        .out_fComplete(U2Tx_fComplete)
    );
*/

endmodule

2023/wbMaster/sim/waveform.vcd
$version Generated by VerilatedVcd $end
$date 12/08/22 18:07:54 $end
$timescale 1ps $end

 $scope module TOP $end
  $var wire 32 _ Rx_wait [31:0] $end
  $var wire  8 e U2Tx_DataByte [7:0] $end
  $var wire  1 d U2Tx_Start $end
  $var wire  1 f U2Tx_fComplete $end
  $var wire  1 N UART_Rx_done $end
  $var wire  8 M UART_in_data [7:0] $end
  $var wire  1 Z WB2UART_cyc $end
  $var wire  1 W WB2UART_stall $end
  $var wire 34 X WB2UART_word [33:0] $end
  $var wire 34 O WB_ctr_w [33:0] $end
  $var wire  1 Q WB_o_cyc $end
  $var wire  1 K clk $end
  $var wire 32 b cmd_index [31:0] $end
  $var wire 32 R io_wb_data [31:0] $end
  $var wire 32 S o_wb_addr [31:0] $end
  $var wire  1 U o_wb_cyc $end
  $var wire  1 V o_wb_stb $end
  $var wire  1 T o_wb_we $end
  $var wire  1 L rst $end
  $var wire 32 c slave_adresa [31:0] $end
  $var wire 32 [ tst1 [31:0] $end
  $var wire 32 \ tst2 [31:0] $end
  $var wire 32 ] tst3 [31:0] $end
  $var wire 32 ^ tst4 [31:0] $end
  $var wire 32 ` wait_A_cnt [31:0] $end
  $var wire 32 a wait_cnt [31:0] $end
  $scope module top_WbMaster $end
   $var wire 32 i KBA [31:0] $end
   $var wire 32 _ Rx_wait [31:0] $end
   $var wire  8 e U2Tx_DataByte [7:0] $end
   $var wire  1 d U2Tx_Start $end
   $var wire  1 f U2Tx_fComplete $end
   $var wire  1 N UART_Rx_done $end
   $var wire  8 M UART_in_data [7:0] $end
   $var wire  1 Z WB2UART_cyc $end
   $var wire  1 W WB2UART_stall $end
   $var wire 34 X WB2UART_word [33:0] $end
   $var wire 34 O WB_ctr_w [33:0] $end
   $var wire  1 Q WB_o_cyc $end
   $var wire  1 K clk $end
   $var wire 32 b cmd_index [31:0] $end
   $var wire  1 # i_wb_ack $end
   $var wire 32 R io_wb_data [31:0] $end
   $var wire 32 S o_wb_addr [31:0] $end
   $var wire  1 U o_wb_cyc $end
   $var wire  1 V o_wb_stb $end
   $var wire  1 T o_wb_we $end
   $var wire  1 L rst $end
   $var wire 32 c slave_adresa [31:0] $end
   $var wire 32 [ tst1 [31:0] $end
   $var wire 32 \ tst2 [31:0] $end
   $var wire 32 ] tst3 [31:0] $end
   $var wire 32 ^ tst4 [31:0] $end
   $var wire 32 ` wait_A_cnt [31:0] $end
   $var wire 32 a wait_cnt [31:0] $end
   $scope module U2wb $end
    $var wire  8 M UART_in_data [7:0] $end
    $var wire  1 N UART_rx_done $end
    $var wire  1 % UART_rx_done_1p $end
    $var wire 34 O WB_ctr_w [33:0] $end
    $var wire 34 ( WB_ctr_w_o [33:0] $end
    $var wire 34 & WB_ctr_w_r [33:0] $end
    $var wire  1 Q WB_o_cyc $end
    $var wire  1 * WB_o_cyc_r $end
    $var wire  5 $ asciiToBits [4:0] $end
    $var wire  1 K clk $end
    $var wire  1 L rst $end
   $upscope $end
   $scope module WBM $end
    $var wire  1 ? Rout_WB2UART_cyc $end
    $var wire 34 = Rout_WB_ctr_r [33:0] $end
    $var wire  1 K clk $end
    $var wire  2 4 i_WB_cmd [1:0] $end
    $var wire  1 - i_cmd_addr $end
    $var wire  1 , i_cmd_bus $end
    $var wire  1 . i_cmd_special $end
    $var wire  1 + i_cmd_wr $end
    $var wire  1 # i_wb_ack $end
    $var wire 34 O in_WB_ctr_w [33:0] $end
    $var wire  1 Q in_WB_o_cyc $end
    $var wire 32 R io_wb_data [31:0] $end
    $var wire 32 S o_wb_addr [31:0] $end
    $var wire  1 U o_wb_cyc $end
    $var wire  1 V o_wb_stb $end
    $var wire  1 T o_wb_we $end
    $var wire  1 Z out_WB2UART_cyc $end
    $var wire 34 X out_WB2UART_word [33:0] $end
    $var wire  1 7 r_cmd_bus $end
    $var wire  1 6 r_cmd_bus_old $end
    $var wire 32 < rio_wb_data [31:0] $end
    $var wire 32 5 ro_wb_addr [31:0] $end
    $var wire  1 9 ro_wb_cyc $end
    $var wire  1 : ro_wb_stb $end
    $var wire  1 ; ro_wb_we $end
    $var wire  1 L rst $end
    $var wire  1 / w_cmd_addr $end
    $var wire  1 3 w_cmd_bus $end
    $var wire  1 8 w_cmd_bus_r $end
    $var wire  1 2 w_cmd_read $end
    $var wire  1 1 w_cmd_rst $end
    $var wire  1 0 w_cmd_write $end
   $upscope $end
   $scope module WBmemory $end
    $var wire  1 K clk $end
    $var wire 32 S i_wb_addr [31:0] $end
    $var wire  1 U i_wb_cyc $end
    $var wire  1 V i_wb_stb $end
    $var wire  1 T i_wb_we $end
    $var wire 32 R io_wb_data [31:0] $end
    $var wire  1 # o_wb_ack $end
    $var wire  1 @ read_enable $end
    $var wire  1 # ro_wb_ack $end
    $var wire 32 A rout_wb_data [31:0] $end
    $var wire  1 L rst $end
   $upscope $end
   $scope module wb2U $end
    $var wire  5 F Rout_DataByte [4:0] $end
    $var wire  1 K clk $end
    $var wire  1 Z in_WB2UART_cyc $end
    $var wire 34 X in_WB2UART_word [33:0] $end
    $var wire  1 f in_fComplete $end
    $var wire  1 C in_fComplete_old $end
    $var wire  1 g in_fComplete_r $end
    $var wire  4 D index [3:0] $end
    $var wire  8 e out_DataByte [7:0] $end
    $var wire  7 h out_DataByte2 [6:0] $end
    $var wire  1 d out_Start $end
    $var wire  1 W out_WB2UART_stall $end
    $var wire  1 I rOut_Start $end
    $var wire  1 J r_WB2UART_stall $end
    $var wire  1 E r_fComplete_r_old $end
    $var wire 32 G regInWord [31:0] $end
    $var wire  1 L rst $end
    $var wire  1 B ted $end
    $var wire  1 H test2 $end
   $upscope $end
  $upscope $end
 $upscope $end
$enddefinitions $end


#0
0#
b00000 $
0%
b0000000000000000000000000000000000 &
b0000000000000000000000000000000000 (
0*
0+
0,
0-
0.
0/
00
01
12
13
b00 4
b00000000000000000000000000000000 5
06
07
08
09
0:
0;
b00000000000000000000000000000000 <
b0000000000000000000000000000000000 =
0?
0@
b00000000000000000000000000000000 A
0B
0C
b0000 D
0E
b00000 F
b00000000000000000000000000000000 G
0H
0I
0J
1K
1L
b00000000 M
0N
b0000000000000000000000000000000000 O
0Q
b00000000000000000000000000000000 R
b00000000000000000000000000000000 S
0T
0U
0V
0W
b0000000000000000000000000000000000 X
0Z
b00000000000000000000000000000000 [
b00000000000000000000000000000000 \
b00000000000000000000000000000000 ]
b00000000000000000000000000000000 ^
b00000000000000000000000000000000 _
b00000000000000000000000000000000 `
b00000000000000000000000000000000 a
b00000000000000000000000000000000 b
b00000000000000000000000000000000 c
0d
b00110000 e
0f
0g
b0110000 h
b00000000000000000000000000000101 i
#1
0K
#2
1K
#3
0K
#4
1K
#5
0K
0L
#6
1K
#7
0K
#8
1K
#9
0K
#10
1K
#11
0K
#12
1K
#13
0K
#14
1K
#15
0K
#16
1K
#17
0K
#18
1K
#19
0K
#20
1K
b01010011 M
1N
b00000000000000000000000001000001 _
#21
0K
#22
b10011 $
1%
1K
0N
b00000000000000000000000000001000 ^
#23
0K
#24
0%
b1100000000000000000000000000000000 &
1*
1K
1Q
b00000000000000000000000000000111 ^
#25
0K
#26
0*
1,
17
18
1K
0Q
b00000000000000000000000000000110 ^
#27
0K
#28
16
07
08
19
1:
1K
1U
1V
b00000000000000000000000000000101 ^
#29
0K
#30
1#
06
0:
1@
b00000000000000000000000000000001 A
1K
b00000000000000000000000000000001 R
0V
b00000000000000000000000000000100 ^
#31
0K
#32
0#
09
b00000000000000000000000000000001 <
b0000000000000000000000000000000001 =
1?
0@
1K
b00000000000000000000000000000000 R
0U
b0000000000000000000000000000000001 X
1Z
b00000000000000000000000000000011 ^
#33
0K
#34
b00000000000000000000000000000000 <
0?
1B
b1000 D
b10000 F
b00000000000000000000000000000001 G
1I
1J
1K
1W
0Z
b00000000000000000000000000000010 ^
1d
b01010010 e
b1010010 h
#35
0K
#36
0B
0I
1K
b00000000000000000000000000000001 ^
0d
#37
0K
#38
1K
1N
b00000000000000000000000000000000 ^
#39
0K
#40
1%
1K
0N
b00000000000000000000000000001000 ^
#41
0K
#42
0%
b1100000000000000000000000000000000 (
1*
11
02
03
b11 4
1K
b1100000000000000000000000000000000 O
1Q
b00000000000000000000000000000111 ^
#43
0K
#44
0*
0,
17
18
b1100000000000000000000000000000001 =
1?
1K
0Q
b1100000000000000000000000000000001 X
1Z
b00000000000000000000000000000110 ^
#45
0K
#46
16
07
08
19
1:
b0000 D
b00000000000000000000000000000000 G
0J
1K
1U
1V
0W
b00000000000000000000000000000101 ^
#47
0K
#48
1#
06
0:
1@
1K
b00000000000000000000000000000001 R
0V
b00000000000000000000000000000100 ^
#49
0K
#50
0#
09
b00000000000000000000000000000001 <
0@
1K
b00000000000000000000000000000000 R
0U
b00000000000000000000000000000011 ^
#51
0K
#52
b00000000000000000000000000000000 <
1K
b00000000000000000000000000000010 ^
#53
0K
#54
1K
b00000000000000000000000000000001 ^
#55
0K
#56
1K
1N
b00000000000000000000000000000000 ^
#57
0K
#58
1%
1K
0N
b00000000000000000000000000001000 ^
#59
0K
#60
0%
1*
1K
1Q
b00000000000000000000000000000111 ^
#61
0K
#62
0*
17
18
1K
0Q
b00000000000000000000000000000110 ^
#63
0K
#64
16
07
08
19
1:
1K
1U
1V
b00000000000000000000000000000101 ^
#65
0K
#66
1#
06
0:
1@
1K
b00000000000000000000000000000001 R
0V
b00000000000000000000000000000100 ^
#67
0K
#68
0#
09
b00000000000000000000000000000001 <
0@
1K
b00000000000000000000000000000000 R
0U
b00000000000000000000000000000011 ^
#69
0K
#70
b00000000000000000000000000000000 <
1K
b00000000000000000000000000000010 ^
#71
0K
#72
1K
b00000000000000000000000000000001 ^
#73
0K
#74
1K
1N
b00000000000000000000000000000000 ^
#75
0K
#76
1%
1K
0N
b00000000000000000000000000001000 ^
#77
0K
#78
0%
1*
1K
1Q
b00000000000000000000000000000111 ^
#79
0K
#80
0*
17
18
1K
0Q
b00000000000000000000000000000110 ^
#81
0K
#82
16
07
08
19
1:
1K
1U
1V
b00000000000000000000000000000101 ^
#83
0K
#84
1#
06
0:
1@
1K
b00000000000000000000000000000001 R
0V
b00000000000000000000000000000100 ^
#85
0K
#86
0#
09
b00000000000000000000000000000001 <
0@
1K
b00000000000000000000000000000000 R
0U
b00000000000000000000000000000011 ^
#87
0K
#88
b00000000000000000000000000000000 <
1K
b00000000000000000000000000000010 ^
#89
0K
#90
1K
b00000000000000000000000000000001 ^
#91
0K
#92
1K
1N
b00000000000000000000000000000000 ^
#93
0K
#94
1%
1K
0N
b00000000000000000000000000001000 ^
#95
0K
#96
0%
1*
1K
1Q
b00000000000000000000000000000111 ^
#97
0K
#98
0*
17
18
1K
0Q
b00000000000000000000000000000110 ^
#99
0K
#100
16
07
08
19
1:
1K
1U
1V
b00000000000000000000000000000101 ^
#101
0K
#102
1#
06
0:
1@
1K
b00000000000000000000000000000001 R
0V
b00000000000000000000000000000100 ^
#103
0K
#104
0#
09
b00000000000000000000000000000001 <
0@
1K
b00000000000000000000000000000000 R
0U
b00000000000000000000000000000011 ^
#105
0K
#106
b00000000000000000000000000000000 <
1K
b00000000000000000000000000000010 ^
#107
0K
#108
1K
b00000000000000000000000000000001 ^
#109
0K
#110
1K
1N
b00000000000000000000000000000000 ^
#111
0K
#112
1%
1K
0N
b00000000000000000000000000001000 ^
#113
0K
#114
0%
1*
1K
1Q
b00000000000000000000000000000111 ^
#115
0K
#116
0*
17
18
1K
0Q
b00000000000000000000000000000110 ^
#117
0K
#118
16
07
08
19
1:
1K
1U
1V
b00000000000000000000000000000101 ^
#119
0K
#120
1#
06
0:
1@
1K
b00000000000000000000000000000001 R
0V
b00000000000000000000000000000100 ^
#121
0K
#122
0#
09
b00000000000000000000000000000001 <
0@
1K
b00000000000000000000000000000000 R
0U
b00000000000000000000000000000011 ^
#123
0K
#124
b00000000000000000000000000000000 <
1K
b00000000000000000000000000000010 ^
#125
0K
#126
1K
b00000000000000000000000000000001 ^
#127
0K
#128
1K
b01000001 M
1N
b00000000000000000000000000000000 ^
#129
0K
#130
b10010 $
1%
1K
0N
b00000000000000000000000000001000 ^
b00000000000000000000000000110100 _
b00000000000000000000000000000001 b
#131
0K
#132
0%
b1000000000000000000000000000000000 &
1*
1K
1Q
b00000000000000000000000000000111 ^
#133
0K
#134
0*
17
18
1K
0Q
b00000000000000000000000000000110 ^
#135
0K
#136
16
07
08
19
1:
1K
1U
1V
b00000000000000000000000000000101 ^
#137
0K
#138
1#
06
0:
1@
1K
b00000000000000000000000000000001 R
0V
b00000000000000000000000000000100 ^
#139
0K
#140
0#
09
b00000000000000000000000000000001 <
0@
1K
b00000000000000000000000000000000 R
0U
b00000000000000000000000000000011 ^
#141
0K
#142
b00000000000000000000000000000000 <
1K
b00000000000000000000000000000010 ^
#143
0K
#144
1K
b00000000000000000000000000000001 ^
#145
0K
#146
1K
b00110100 M
1N
b00000000000000000000000000000000 ^
#147
0K
#148
b00100 $
1%
1K
0N
b00000000000000000000000000001000 ^
b00000000000000000000000000110000 _
b00000000000000000000000000000010 b
#149
0K
#150
0%
b1000000000000000000000000000000100 &
1K
b00000000000000000000000000000111 ^
#151
0K
#152
1K
b00000000000000000000000000000110 ^
#153
0K
#154
1K
b00000000000000000000000000000101 ^
#155
0K
#156
1K
b00000000000000000000000000000100 ^
#157
0K
#158
1K
b00000000000000000000000000000011 ^
#159
0K
#160
1K
b00000000000000000000000000000010 ^
#161
0K
#162
1K
b00000000000000000000000000000001 ^
#163
0K
#164
1K
b00110000 M
1N
b00000000000000000000000000000000 ^
#165
0K
#166
b00000 $
1%
1K
0N
b00000000000000000000000000001000 ^
b00000000000000000000000001010111 _
b00000000000000000000000000000011 b
#167
0K
#168
0%
b1000000000000000000000000001000000 &
1K
b00000000000000000000000000000111 ^
#169
0K
#170
1K
b00000000000000000000000000000110 ^
#171
0K
#172
1K
b00000000000000000000000000000101 ^
#173
0K
#174
1K
b00000000000000000000000000000100 ^
#175
0K
#176
1K
b00000000000000000000000000000011 ^
#177
0K
#178
1K
b00000000000000000000000000000010 ^
#179
0K
#180
1K
b00000000000000000000000000000001 ^
#181
0K
#182
1K
b01010111 M
1N
b00000000000000000000000000000000 ^
#183
0K
#184
b10001 $
1%
1K
0N
b00000000000000000000000000001000 ^
b00000000000000000000000000110101 _
b00000000000000000000000000000001 a
b00000000000000000000000000000100 b
#185
0K
#186
0%
b0100000000000000000000000000000000 &
b1000000000000000000000000001000000 (
1*
1/
01
b10 4
1K
b1000000000000000000000000001000000 O
1Q
b00000000000000000000000000000111 ^
#187
0K
#188
0*
1-
b00000000000000000000000001000000 5
17
18
b00000000000000000000000001000000 <
0?
1K
0Q
b00000000000000000000000001000000 S
0Z
b00000000000000000000000000000110 ^
#189
0K
#190
16
07
08
1K
b00000000000000000000000000000101 ^
#191
0K
#192
06
1K
b00000000000000000000000000000100 ^
#193
0K
#194
1K
b00000000000000000000000000000011 ^
#195
0K
