library/communication/SPI/SPI_DAC.sv
module SPI_DAC (input clk, input rst, input ST_rise, output n_CS, output SCK, output SDI);//Start Transfer

parameter SCK_div = 10 / 2; 	///5000/2
 
reg [3:0] cfg  = 4'b1100;
reg [7:0] data = 120;

wire [15:0] data_out;
reg [3:0] cnt = 0;
reg [$clog2(SCK_div):0] SCK_cnt = 0;
reg r_SCK = 0;
reg r_SDI;
reg r_CS;
reg [4:0] index = 0;

reg r_SCK_fall;

wire w_SCK_fall;

always @(posedge clk) begin

	if(r_CS == 0) begin
	
		if(SCK_cnt < SCK_div) begin
			SCK_cnt <= SCK_cnt + 1;
		end else begin
			SCK_cnt <= 0;
			r_SCK <= ~ r_SCK;
		end
	
	end
	
	
	r_SCK_fall <= r_SCK;
end


assign data_out = {{4{1'b0}},{data,cfg}};
assign w_SCK_fall = r_SCK_fall & (!r_SCK);

always @(posedge clk) begin	// datovy signal se bude menit pri falling edge

	if(rst)begin
		r_CS <= 1;
		index <= 15;
	end else begin
		
		if(ST_rise) begin
			index <= 0;
			r_SDI <= data_out[index[3:0]];
			r_CS  <= 0;
		end
		else begin
			if((index < 15) && (w_SCK_fall)) begin
				index <= index + 1;
				r_SDI <= data_out[index[3:0]];
				
			end else if(index > 15) begin
				r_CS  <= 1;
			end
			
		end 
	end
end


assign n_CS = r_CS;
assign SCK = r_SCK;
assign SDI = r_SDI;

//assign data_out = {{4{1'b0}},{}}

endmodule;

library/communication/SPI/waveform.vcd
$version Generated by VerilatedVcd $end
$date 03/22/22 19:53:16 $end
$timescale 1ps $end

 $scope module TOP $end
  $var wire  1 . SCK $end
  $var wire  1 / SDI $end
  $var wire  1 , ST_rise $end
  $var wire  1 * clk $end
  $var wire  1 - n_CS $end
  $var wire  1 + rst $end
  $scope module SPI_DAC $end
   $var wire  1 . SCK $end
   $var wire  4 # SCK_cnt [3:0] $end
   $var wire 32 0 SCK_div [31:0] $end
   $var wire  1 / SDI $end
   $var wire  1 , ST_rise $end
   $var wire  4 1 cfg [3:0] $end
   $var wire  1 * clk $end
   $var wire  4 4 cnt [3:0] $end
   $var wire  8 2 data [7:0] $end
   $var wire 16 3 data_out [15:0] $end
   $var wire  5 ' index [4:0] $end
   $var wire  1 - n_CS $end
   $var wire  1 & r_CS $end
   $var wire  1 $ r_SCK $end
   $var wire  1 ( r_SCK_fall $end
   $var wire  1 % r_SDI $end
   $var wire  1 + rst $end
   $var wire  1 ) w_SCK_fall $end
  $upscope $end
 $upscope $end
$enddefinitions $end


#0
b0000 #
0$
0%
0&
b00000 '
1(
1)
1*
1+
0,
0-
0.
0/
b00000000000000000000000000000101 0
b1100 1
b01111000 2
b0000011110001100 3
b0000 4
#1
0*
#2
b0001 #
1&
b01111 '
0(
0)
1*
1-
#3
0*
#4
1*
#5
0*
#6
1*
0+
#7
0*
#8
1*
#9
0*
#10
1*
#11
0*
#12
1*
1,
#13
0*
#14
0&
b00000 '
1*
0,
0-
#15
0*
#16
b0010 #
1*
#17
0*
#18
b0011 #
1*
#19
0*
#20
b0100 #
1*
#21
0*
#22
b0101 #
1*
#23
0*
#24
b0000 #
1$
1*
1.
#25
0*
#26
b0001 #
1(
1*
#27
0*
#28
b0010 #
1*
#29
0*
#30
b0011 #
1*
#31
0*
#32
b0100 #
1*
#33
0*
#34
b0101 #
1*
#35
0*
#36
b0000 #
0$
1)
1*
0.
#37
0*
#38
b0001 #
b00001 '
0(
0)
1*
#39
0*
#40
b0010 #
1*
#41
0*
#42
b0011 #
1*
#43
0*
#44
b0100 #
1*
#45
0*
#46
b0101 #
1*
#47
0*
#48
b0000 #
1$
1*
1.
#49
0*
#50
b0001 #
1(
1*
#51
0*
#52
b0010 #
1*
#53
0*
#54
b0011 #
1*
#55
0*
#56
b0100 #
1*
#57
0*
#58
b0101 #
1*
#59
0*
#60
b0000 #
0$
1)
1*
0.
#61
0*
#62
b0001 #
b00010 '
0(
0)
1*
#63
0*
#64
b0010 #
1*
#65
0*
#66
b0011 #
1*
#67
0*
#68
b0100 #
1*
#69
0*
#70
b0101 #
1*
#71
0*
#72
b0000 #
1$
1*
1.
#73
0*
#74
b0001 #
1(
1*
#75
0*
#76
b0010 #
1*
#77
0*
#78
b0011 #
1*
#79
0*
#80
b0100 #
1*
#81
0*
#82
b0101 #
1*
#83
0*
#84
b0000 #
0$
1)
1*
0.
#85
0*
#86
b0001 #
1%
b00011 '
0(
0)
1*
1/
#87
0*
#88
b0010 #
1*
#89
0*
#90
b0011 #
1*
#91
0*
#92
b0100 #
1*
#93
0*
#94
b0101 #
1*
#95
0*
#96
b0000 #
1$
1*
1.
#97
0*
#98
b0001 #
1(
1*
#99
0*
#100
b0010 #
1*
#101
0*
#102
b0011 #
1*
#103
0*
#104
b0100 #
1*
#105
0*
#106
b0101 #
1*
#107
0*
#108
b0000 #
0$
1)
1*
0.
#109
0*
#110
b0001 #
b00100 '
0(
0)
1*
#111
0*
#112
b0010 #
1*
#113
0*
#114
b0011 #
1*
#115
0*
#116
b0100 #
1*
#117
0*
#118
b0101 #
1*
#119
0*
#120
b0000 #
1$
1*
1.
#121
0*
#122
b0001 #
1(
1*
#123
0*
#124
b0010 #
1*
#125
0*
#126
b0011 #
1*
#127
0*
#128
b0100 #
1*
#129
0*
#130
b0101 #
1*
#131
0*
#132
b0000 #
0$
1)
1*
0.
#133
0*
#134
b0001 #
0%
b00101 '
0(
0)
1*
0/
#135
0*
#136
b0010 #
1*
#137
0*
#138
b0011 #
1*
#139
0*
#140
b0100 #
1*
#141
0*
#142
b0101 #
1*
#143
0*
#144
b0000 #
1$
1*
1.
#145
0*
#146
b0001 #
1(
1*
#147
0*
#148
b0010 #
1*
#149
0*
#150
b0011 #
1*
#151
0*
#152
b0100 #
1*
#153
0*
#154
b0101 #
1*
#155
0*
#156
b0000 #
0$
1)
1*
0.
#157
0*
#158
b0001 #
b00110 '
0(
0)
1*
#159
0*
#160
b0010 #
1*
#161
0*
#162
b0011 #
1*
#163
0*
#164
b0100 #
1*
#165
0*
#166
b0101 #
1*
#167
0*
#168
b0000 #
1$
1*
1.
#169
0*
#170
b0001 #
1(
1*
#171
0*
#172
b0010 #
1*
#173
0*
#174
b0011 #
1*
#175
0*
#176
b0100 #
1*
#177
0*
#178
b0101 #
1*
#179
0*
#180
b0000 #
0$
1)
1*
0.
#181
0*
#182
b0001 #
b00111 '
0(
0)
1*
#183
0*
#184
b0010 #
1*
#185
0*
#186
b0011 #
1*
#187
0*
#188
b0100 #
1*
#189
0*
#190
b0101 #
1*
#191
0*
#192
b0000 #
1$
1*
1.
#193
0*
#194
b0001 #
1(
1*
#195
0*
#196
b0010 #
1*
#197
0*
#198
b0011 #
1*
#199
0*
#200
b0100 #
1*
#201
0*
#202
b0101 #
1*
#203
0*
#204
b0000 #
0$
1)
1*
0.
#205
0*
#206
b0001 #
1%
b01000 '
0(
0)
1*
1/
#207
0*
#208
b0010 #
1*
#209
0*
#210
b0011 #
1*
#211
0*
#212
b0100 #
1*
#213
0*
#214
b0101 #
1*
#215
0*
#216
b0000 #
1$
1*
1.
#217
0*
#218
b0001 #
1(
1*
#219
0*
#220
b0010 #
1*
#221
0*
#222
b0011 #
1*
#223
0*
#224
b0100 #
1*
#225
0*
#226
b0101 #
1*
#227
0*
#228
b0000 #
0$
1)
1*
0.
#229
0*
#230
b0001 #
b01001 '
0(
0)
1*
#231
0*
#232
b0010 #
1*
#233
0*
#234
b0011 #
1*
#235
0*
#236
b0100 #
1*
#237
0*
#238
b0101 #
1*
#239
0*
#240
b0000 #
1$
1*
1.
#241
0*
#242
b0001 #
1(
1*
#243
0*
#244
b0010 #
1*
#245
0*
#246
b0011 #
1*
#247
0*
#248
b0100 #
1*
#249
0*
#250
b0101 #
1*
#251
0*
#252
b0000 #
0$
1)
1*
0.
#253
0*
#254
b0001 #
b01010 '
0(
0)
1*
#255
0*
#256
b0010 #
1*
#257
0*
#258
b0011 #
1*
#259
0*
#260
b0100 #
1*
#261
0*
#262
b0101 #
1*
#263
0*
#264
b0000 #
1$
1*
1.
#265
0*
#266
b0001 #
1(
1*
#267
0*
#268
b0010 #
1*
#269
0*
#270
b0011 #
1*
#271
0*
#272
b0100 #
1*
#273
0*
#274
b0101 #
1*
#275
0*
#276
b0000 #
0$
1)
1*
0.
#277
0*
#278
b0001 #
b01011 '
0(
0)
1*
#279
0*
#280
b0010 #
1*
#281
0*
#282
b0011 #
1*
#283
0*
#284
b0100 #
1*
#285
0*
#286
b0101 #
1*
#287
0*
#288
b0000 #
1$
1*
1.
#289
0*
#290
b0001 #
1(
1*
#291
0*
#292
b0010 #
1*
#293
0*
#294
b0011 #
1*
#295
0*
#296
b0100 #
1*
#297
0*
#298
b0101 #
1*
#299
0*
#300
b0000 #
0$
1)
1*
0.
#301
0*
#302
b0001 #
0%
b01100 '
0(
0)
1*
0/
#303
0*
#304
b0010 #
1*
#305
0*
#306
b0011 #
1*
#307
0*
#308
b0100 #
1*
#309
0*
#310
b0101 #
1*
#311
0*
#312
b0000 #
1$
1*
1.
#313
0*
#314
b0001 #
1(
1*
#315
0*
#316
b0010 #
1*
#317
0*
#318
b0011 #
1*
#319
0*
#320
b0100 #
1*
#321
0*
#322
b0101 #
1*
#323
0*
#324
b0000 #
0$
1)
1*
0.
#325
0*
#326
b0001 #
b01101 '
0(
0)
1*
#327
0*
#328
b0010 #
1*
#329
0*
#330
b0011 #
1*
#331
0*
#332
b0100 #
1*
#333
0*
#334
b0101 #
1*
#335
0*
#336
b0000 #
1$
1*
1.
#337
0*
#338
b0001 #
1(
1*
#339
0*
#340
b0010 #
1*
#341
0*
#342
b0011 #
1*
#343
0*
#344
b0100 #
1*
#345
0*
#346
b0101 #
1*
#347
0*
#348
b0000 #
0$
1)
1*
0.
#349
0*
#350
b0001 #
b01110 '
0(
0)
1*
#351
0*
#352
b0010 #
1*
#353
0*
#354
b0011 #
1*
#355
0*
#356
b0100 #
1*
#357
0*
#358
b0101 #
1*
#359
0*
#360
b0000 #
1$
1*
1.
#361
0*
#362
b0001 #
1(
1*
#363
0*
#364
b0010 #
1*
#365
0*
#366
b0011 #
1*
#367
0*
#368
b0100 #
1*
#369
0*
#370
b0101 #
1*
#371
0*
#372
b0000 #
0$
1)
1*
0.
#373
0*
#374
b0001 #
b01111 '
0(
0)
1*
#375
0*
#376
b0010 #
1*
#377
0*
#378
b0011 #
1*
#379
0*
#380
b0100 #
1*
#381
0*
#382
b0101 #
1*
#383
0*
#384
b0000 #
1$
1*
1.
#385
0*
#386
b0001 #
1(
1*
#387
0*
#388
b0010 #
1*
#389
0*
#390
b0011 #
1*
#391
0*
#392
b0100 #
1*
#393
0*
#394
b0101 #
1*
#395
0*
#396
b0000 #
0$
1)
1*
0.
#397
0*
#398
b0001 #
0(
0)
1*
#399
0*
#400
b0010 #
1*
#401
0*
#402
b0011 #
1*
#403
0*
#404
b0100 #
1*
#405
0*
#406
b0101 #
1*
#407
0*
#408
b0000 #
1$
1*
1.
#409
0*
#410
b0001 #
1(
1*
#411
0*
#412
b0010 #
1*
#413
0*
#414
b0011 #
1*
#415
0*
#416
b0100 #
1*
#417
0*
#418
b0101 #
1*
#419
0*
#420
b0000 #
0$
1)
1*
0.
#421
0*
#422
b0001 #
0(
0)
1*
#423
0*
#424
b0010 #
1*
#425
0*
#426
b0011 #
1*
#427
0*
#428
b0100 #
1*
#429
0*
#430
b0101 #
1*
#431
0*
#432
b0000 #
1$
1*
1.
#433
0*
#434
b0001 #
1(
1*
#435
0*
#436
b0010 #
1*
#437
0*
#438
b0011 #
1*
#439
0*
#440
b0100 #
1*
#441
0*
#442
b0101 #
1*
#443
0*
#444
b0000 #
0$
1)
1*
0.
#445
0*
#446
b0001 #
0(
0)
1*
#447
0*
#448
b0010 #
1*
#449
0*
#450
b0011 #
1*
#451
0*
#452
b0100 #
1*
#453
0*
#454
b0101 #
1*
#455
0*
#456
b0000 #
1$
1*
1.
#457
0*
#458
b0001 #
1(
1*
#459
0*
#460
b0010 #
1*
#461
0*
#462
b0011 #
1*
#463
0*
#464
b0100 #
1*
#465
0*
#466
b0101 #
1*
#467
0*
#468
b0000 #
0$
1)
1*
0.
#469
0*
#470
b0001 #
0(
0)
1*
#471
0*
#472
b0010 #
1*
#473
0*
#474
b0011 #
1*
#475
0*
#476
b0100 #
1*
#477
0*
#478
b0101 #
1*
#479
0*
#480
b0000 #
1$
1*
1.
#481
0*
#482
b0001 #
1(
1*
#483
0*
#484
b0010 #
1*
#485
0*
#486
b0011 #
1*
#487
0*
#488
b0100 #
1*
#489
0*
#490
b0101 #
1*
#491
0*
#492
b0000 #
0$
1)
1*
0.
#493
0*
#494
b0001 #
0(
0)
1*
#495
0*
#496
b0010 #
1*
#497
0*
#498
b0011 #
1*
