test/alu.sv
/****** alu.sv ******/
typedef enum logic [1:0] {
     add     = 2'h1,
     sub     = 2'h2,
     nop     = 2'h0
} operation_t /*verilator public*/;

module alu #(
        parameter WIDTH = 6
) (
        input clk,
        input rst,

        input  operation_t  op_in,
        input  [WIDTH-1:0]  a_in,
        input  [WIDTH-1:0]  b_in,
        input               in_valid,

        output logic [WIDTH-1:0]  out,
        output logic              out_valid
);

        operation_t  op_in_r;
        logic  [WIDTH-1:0]  a_in_r;
        logic  [WIDTH-1:0]  b_in_r;
        logic               in_valid_r;
        logic  [WIDTH-1:0]  result;

        // Register all inputs
        always_ff @ (posedge clk, posedge rst) begin
                if (rst) begin
                        op_in_r     <= '0;
                        a_in_r      <= '0;
                        b_in_r      <= '0;
                        in_valid_r  <= '0;
                end else begin
                        op_in_r    <= op_in;
                        a_in_r     <= a_in;
                        b_in_r     <= b_in;
                        in_valid_r <= in_valid;
                end
        end

        // Compute the result
        always_comb begin
                result = '0;
                if (in_valid_r) begin
                        case (op_in_r)
                                add: result = a_in_r + b_in_r;
                                sub: result = a_in_r + (~b_in_r+1'b1);
                                default: result = '0;
                        endcase
                end
        end

        // Register outputs
        always_ff @ (posedge clk, posedge rst) begin
                if (rst) begin
                        out       <= '0;
                        out_valid <= '0;
                end else begin
                        out       <= result;
                        out_valid <= in_valid_r;
                end
        end

endmodule;

test/obj_dir/waveform.vcd
$version Generated by VerilatedVcd $end
$date 01/07/22 18:53:42 $end
$timescale 1ps $end

 $scope module TOP $end
  $var wire  6 + a_in [5:0] $end
  $var wire  6 , b_in [5:0] $end
  $var wire  1 ( clk $end
  $var wire  1 - in_valid $end
  $var wire  2 * op_in [1:0] $end
  $var wire  6 . out [5:0] $end
  $var wire  1 / out_valid $end
  $var wire  1 ) rst $end
  $scope module alu $end
   $var wire 32 0 WIDTH [31:0] $end
   $var wire  6 + a_in [5:0] $end
   $var wire  6 $ a_in_r [5:0] $end
   $var wire  6 , b_in [5:0] $end
   $var wire  6 % b_in_r [5:0] $end
   $var wire  1 ( clk $end
   $var wire  1 - in_valid $end
   $var wire  1 & in_valid_r $end
   $var wire  2 * op_in [1:0] $end
   $var wire  2 # op_in_r [1:0] $end
   $var wire  6 . out [5:0] $end
   $var wire  1 / out_valid $end
   $var wire  6 ' result [5:0] $end
   $var wire  1 ) rst $end
  $upscope $end
 $upscope $end
$enddefinitions $end


#0
b00 #
b000000 $
b000000 %
0&
b000000 '
1(
0)
b00 *
b000000 +
b000000 ,
0-
b000000 .
0/
b00000000000000000000000000000110 0
#1
0(
#2
1(
#3
0(
1)
#4
1(
#5
0(
#6
1(
0)
#7
0(
#8
1(
#9
0(
#10
1(
#11
0(
#12
1(
#13
0(
#14
1(
#15
0(
#16
1(
#17
0(
#18
1(
#19
0(
#20
1(
#21
0(
#22
1(
b01 *
b001011 +
b000011 ,
1-
#23
0(
#24
b01 #
b001011 $
b000011 %
1&
b001110 '
1(
0-
#25
0(
#26
0&
b000000 '
1(
b10 *
b010010 +
b000100 ,
1-
b001110 .
1/
#27
0(
#28
b10 #
b010010 $
b000100 %
1&
b001110 '
1(
0-
b000000 .
0/
#29
0(
#30
0&
b000000 '
1(
b001110 .
1/
#31
0(
#32
1(
b000000 .
0/
#33
0(
#34
1(
#35
0(
#36
1(
#37
0(
#38
1(
#39
0(
#40
1(
#41
0(
#42
1(
#43
0(
#44
1(
#45
0(
#46
1(
b01 *
b001100 +
b000001 ,
1-
#47
0(
#48
b01 #
b001100 $
b000001 %
1&
b001101 '
1(
0-
#49
0(
#50
0&
b000000 '
1(
b001101 .
1/
#51
0(
#52
1(
b000000 .
0/
#53
0(
#54
1(
#55
0(
#56
1(
#57
0(
#58
1(
#59
0(
#60
1(
b10 *
b010010 +
b000011 ,
1-
#61
0(
#62
b10 #
b010010 $
b000011 %
1&
b001111 '
1(
0-
#63
0(
#64
0&
b000000 '
1(
b001111 .
1/
#65
0(
#66
1(
b000000 .
0/
#67
0(
#68
1(
#69
0(
#70
1(
#71
0(
#72
1(
b01 *
b010001 +
b000010 ,
1-
#73
0(
#74
b01 #
b010001 $
b000010 %
1&
b010011 '
1(
0-
#75
0(
#76
0&
b000000 '
1(
b010011 .
1/
#77
0(
#78
1(
b000000 .
0/
#79
0(
#80
1(
#81
0(
#82
1(
#83
0(
#84
1(
#85
0(
#86
1(
#87
0(
#88
1(
#89
0(
#90
1(
#91
0(
#92
1(
#93
0(
#94
1(
#95
0(
#96
1(
b010010 +
b000101 ,
1-
#97
0(
#98
b010010 $
b000101 %
1&
b010111 '
1(
b10 *
b001011 +
#99
0(
#100
b10 #
b001011 $
b000110 '
1(
b001010 +
b010111 .
1/
#101
0(
#102
b001010 $
b000101 '
1(
b01 *
b010100 +
b000010 ,
b000110 .
#103
0(
#104
b01 #
b010100 $
b000010 %
b010110 '
1(
0-
b000101 .
#105
0(
#106
0&
b000000 '
1(
b010110 .
#107
0(
#108
1(
b000000 .
0/
#109
0(
#110
1(
b010001 +
b000100 ,
1-
#111
0(
#112
b010001 $
b000100 %
1&
b010101 '
1(
0-
#113
0(
#114
0&
b000000 '
1(
b010101 .
1/
#115
0(
#116
1(
b000000 .
0/
#117
0(
#118
1(
#119
0(
#120
1(
#121
0(
#122
1(
b10 *
b000001 ,
1-
#123
0(
#124
b10 #
b000001 %
1&
b010000 '
1(
0-
#125
0(
#126
0&
b000000 '
1(
b010000 .
1/
#127
0(
#128
1(
b000000 .
0/
#129
0(
#130
1(
#131
0(
#132
1(
#133
0(
#134
1(
#135
0(
#136
1(
#137
0(
#138
1(
#139
0(
#140
1(
#141
0(
#142
1(
#143
0(
#144
1(
#145
0(
#146
1(
#147
0(
#148
1(
#149
0(
#150
1(
#151
0(
#152
1(
b001100 +
b000101 ,
1-
#153
0(
#154
b001100 $
b000101 %
1&
b000111 '
1(
0-
#155
0(
#156
0&
b000000 '
1(
b000111 .
1/
#157
0(
#158
1(
b000000 .
0/
#159
0(
#160
1(
#161
0(
#162
1(
#163
0(
#164
1(
#165
0(
#166
1(
#167
0(
#168
1(
#169
0(
#170
1(
#171
0(
#172
1(
#173
0(
#174
1(
b001111 +
b000001 ,
1-
#175
0(
#176
b001111 $
b000001 %
1&
b001110 '
1(
0-
#177
0(
#178
0&
b000000 '
1(
b001110 .
1/
#179
0(
#180
1(
b000000 .
0/
